{
"bones": [
	{ "name": "root" },
	{ "name": "hip", "parent": "root", "length": 40.76, "x": 2.52, "y": 159.07, "rotation": -88.19 },
	{ "name": "body", "parent": "hip", "length": 156.27, "x": -0.88, "y": -0.64, "rotation": 169.29 },
	{ "name": "leg_left", "parent": "hip", "length": 63.46, "x": 13.28, "y": 26.31, "rotation": -0.9 },
	{ "name": "leg_right", "parent": "hip", "length": 62.79, "x": 4.66, "y": -11.21, "rotation": -1.8 },
	{ "name": "skirt", "parent": "hip", "length": 41.76, "x": 0.9, "y": 7.91, "rotation": 1.8 },
	{ "name": "calf_left", "parent": "leg_left", "length": 69.73, "x": 63.46, "y": -0.34, "rotation": 3.6 },
	{ "name": "calf_right", "parent": "leg_right", "length": 64.88, "x": 62.79, "rotation": 2.7 },
	{ "name": "head", "parent": "body", "length": 148.73, "x": 150.62, "y": 0.93, "rotation": 4.53 },
	{ "name": "left_shoulder", "parent": "body", "length": 60.48, "x": 139.67, "y": -67.4, "rotation": -165.01 },
	{ "name": "right_shoulder", "parent": "body", "length": 73.73, "x": 141.62, "y": 49.86, "rotation": 169.65 },
	{ "name": "foot_left", "parent": "calf_left", "length": 32.67, "x": 69.73, "y": 0.52, "rotation": -53.56 },
	{ "name": "foot_right", "parent": "calf_right", "length": 31.18, "x": 64.88, "y": 0.26, "rotation": -49.62 },
	{ "name": "hair", "parent": "head", "length": 125.84, "x": 144.32, "y": -11.6, "rotation": -166.7 },
	{ "name": "left_arm", "parent": "left_shoulder", "length": 55.45, "x": 60.49, "y": 0.25, "rotation": -5.39 },
	{ "name": "pony", "parent": "head", "length": 49.46, "x": 143.53, "y": -1.28, "rotation": -169.73 },
	{ "name": "right_arm", "parent": "right_shoulder", "length": 55.58, "x": 73.73, "y": -0.44, "rotation": -0.9 },
	{ "name": "left_hand", "parent": "left_arm", "length": 33.46, "x": 55.44, "rotation": 2.7 },
	{ "name": "right_hand", "parent": "right_arm", "length": 35.55, "x": 55.58, "y": -0.24, "rotation": -5.39 }
],
"slots": [
	{ "name": "weapon", "bone": "right_hand", "attachment": "boss_skin/weapon" },
	{ "name": "hair", "bone": "hair", "attachment": "boss_skin/hair" },
	{ "name": "arm_right", "bone": "right_arm", "attachment": "boss_skin/arm_right" },
	{ "name": "shoulder_right", "bone": "right_shoulder", "attachment": "boss_skin/shoulder_right" },
	{ "name": "leg_right", "bone": "leg_right", "attachment": "boss_skin/leg_right" },
	{ "name": "calf_right", "bone": "calf_right", "attachment": "boss_skin/calf_right" },
	{ "name": "shoe_right", "bone": "foot_right", "attachment": "boss_skin/shoe_right" },
	{ "name": "leg_left", "bone": "leg_left", "attachment": "boss_skin/leg_left" },
	{ "name": "calf_left", "bone": "calf_left", "attachment": "boss_skin/calf_left" },
	{ "name": "shoe_left", "bone": "foot_left", "attachment": "boss_skin/shoe_left" },
	{ "name": "skirt", "bone": "skirt", "attachment": "boss_skin/skirt" },
	{ "name": "body", "bone": "body", "attachment": "boss_skin/body" },
	{ "name": "head", "bone": "head", "attachment": "boss_skin/head" },
	{ "name": "pony", "bone": "pony", "attachment": "boss_skin/pony" },
	{ "name": "arm_left", "bone": "left_arm", "attachment": "boss_skin/arm_left" },
	{ "name": "shoulder_left", "bone": "left_shoulder", "attachment": "boss_skin/shoulder_left" },
	{ "name": "hand_left", "bone": "left_hand", "attachment": "boss_skin/hand_left" },
	{ "name": "bb_sweetcheeks", "bone": "right_hand", "attachment": "bb_sweetcheeks" }
],
"skins": {
	"default": {
		"arm_left": {
			"boss_skin/arm_left": { "x": 24.44, "y": -0.87, "rotation": 89.3, "width": 45, "height": 80 }
		},
		"arm_right": {
			"boss_skin/arm_right": { "x": 19.62, "y": -0.76, "rotation": 110.14, "width": 45, "height": 89 }
		},
		"bb_sweetcheeks": {
			"bb_sweetcheeks": {
				"type": "boundingbox",
				"vertices": [ 48.48501, 31.609352, -14.722595, 27.475616, -37.571915, -486.65744, 139.96335, -473.5145 ]
			}
		},
		"body": {
			"boss_skin/body": { "x": 81.47, "y": -4.54, "rotation": -81.1, "width": 139, "height": 195 }
		},
		"calf_left": {
			"boss_skin/calf_left": { "x": 33.49, "y": 0.27, "rotation": 85.49, "width": 40, "height": 86 }
		},
		"calf_right": {
			"boss_skin/calf_right": { "x": 31.29, "y": -1.07, "rotation": 87.29, "width": 37, "height": 82 }
		},
		"hair": {
			"boss_skin/hair": { "x": 71.44, "y": -18.15, "rotation": 81.06, "width": 258, "height": 251 }
		},
		"hand_left": {
			"boss_skin/hand_left": { "x": 15.28, "y": -1.48, "rotation": 86.6, "width": 40, "height": 50 }
		},
		"head": {
			"boss_skin/faces/attack": { "x": 68.69, "y": -6.81, "rotation": -85.64, "width": 147, "height": 154 },
			"boss_skin/faces/die": { "x": 67.19, "y": 0.69, "rotation": -85.64, "width": 148, "height": 149 },
			"boss_skin/faces/hit": { "x": 74.73, "y": -1.49, "rotation": -85.64, "width": 149, "height": 166 },
			"boss_skin/faces/jump": { "x": 67.46, "y": -2.79, "rotation": -85.64, "width": 149, "height": 151 },
			"boss_skin/faces/run": { "x": 71.88, "y": -0.36, "rotation": -85.64, "width": 142, "height": 149 },
			"boss_skin/faces/scream": { "x": 65.16, "y": -2.33, "rotation": -85.64, "width": 140, "height": 139 },
			"boss_skin/head": { "x": 72.7, "y": -9.75, "rotation": -85.64, "width": 155, "height": 159 }
		},
		"leg_left": {
			"boss_skin/leg_left": { "x": 31.45, "y": 1.75, "rotation": 89.09, "width": 49, "height": 92 }
		},
		"leg_right": {
			"boss_skin/leg_right": { "x": 30.05, "y": -0.11, "rotation": 89.99, "width": 46, "height": 88 }
		},
		"pony": {
			"boss_skin/pony": { "x": 63.73, "y": -14.11, "rotation": 84.09, "width": 207, "height": 199 }
		},
		"shoe_left": {
			"boss_skin/shoe_left": { "x": 12.26, "y": 1.47, "rotation": 139.06, "width": 50, "height": 38 }
		},
		"shoe_right": {
			"boss_skin/shoe_right": { "x": 11.25, "y": 0.68, "rotation": 136.91, "width": 48, "height": 36 }
		},
		"shoulder_left": {
			"boss_skin/shoulder_left": { "x": 22.37, "y": 2.91, "rotation": 83.9, "width": 66, "height": 105 }
		},
		"shoulder_right": {
			"boss_skin/shoulder_right": { "x": 32.01, "y": 1.5, "rotation": 109.24, "width": 63, "height": 97 }
		},
		"skirt": {
			"boss_skin/skirt": { "x": 60.5, "y": 14.7, "rotation": 86.39, "width": 186, "height": 154 }
		},
		"weapon": {
			"boss_skin/hand_right": { "x": 20.34, "y": -1.57, "rotation": 115.54, "width": 40, "height": 48 },
			"boss_skin/weapon": { "x": 23.76, "y": -233.19, "rotation": 115.54, "width": 478, "height": 239 }
		}
	}
},
"animations": {
	"attack": {
		"bones": {
			"right_shoulder": {
				"rotate": [
					{ "time": 0, "angle": -317.58 },
					{ "time": 0.0666, "angle": -144.45 },
					{ "time": 0.1333, "angle": -118.04 },
					{ "time": 0.1666, "angle": -8.72 },
					{ "time": 0.2333, "angle": -6.76 },
					{ "time": 0.4333, "angle": 6.94 },
					{ "time": 0.5333, "angle": -291.63 },
					{ "time": 0.5666, "angle": 8.38 }
				]
			},
			"right_arm": {
				"rotate": [
					{ "time": 0, "angle": 94.45 },
					{ "time": 0.0666, "angle": -50.85 },
					{ "time": 0.1333, "angle": -55.92 },
					{ "time": 0.1666, "angle": 0.73 },
					{ "time": 0.2333, "angle": 0.85 },
					{ "time": 0.4333, "angle": 0.78 },
					{ "time": 0.5333, "angle": -50.65 },
					{ "time": 0.5666, "angle": -146.89 }
				]
			},
			"left_shoulder": {
				"rotate": [
					{ "time": 0, "angle": 36.65 },
					{ "time": 0.0666, "angle": 18.35 },
					{ "time": 0.1333, "angle": 317.54 },
					{ "time": 0.2333, "angle": 344.12, "curve": "stepped" },
					{ "time": 0.3, "angle": 344.12 },
					{ "time": 0.6, "angle": 2.51 }
				]
			},
			"left_arm": {
				"rotate": [
					{ "time": 0, "angle": -108.59 },
					{ "time": 0.0666, "angle": -27.98 },
					{ "time": 0.1333, "angle": -110.7 },
					{ "time": 0.2333, "angle": -33.07, "curve": "stepped" },
					{ "time": 0.3, "angle": -33.07 },
					{ "time": 0.6, "angle": -50.43 }
				]
			},
			"hip": {
				"rotate": [
					{ "time": 0, "angle": 22.88 },
					{ "time": 0.0666, "angle": -45.78 },
					{ "time": 0.1666, "angle": 45.48 },
					{ "time": 0.2333, "angle": 20.62, "curve": "stepped" },
					{ "time": 0.3, "angle": 20.62 }
				],
				"translate": [
					{ "time": 0, "x": 0, "y": -8.14 },
					{ "time": 0.0333, "x": -28.38, "y": 40.75 },
					{ "time": 0.0666, "x": -39.54, "y": 53.49 },
					{ "time": 0.1666, "x": -22.31, "y": -28.31 },
					{ "time": 0.2333, "x": -7.68, "y": -132.49, "curve": "stepped" },
					{ "time": 0.3, "x": -7.68, "y": -132.49 },
					{ "time": 0.5, "x": -7.68, "y": -3.71, "curve": "stepped" },
					{ "time": 0.6, "x": -7.68, "y": -3.71 }
				]
			},
			"leg_right": {
				"rotate": [
					{ "time": 0, "angle": -73.09 },
					{ "time": 0.0333, "angle": -52.06 },
					{ "time": 0.0666, "angle": -8.52 },
					{ "time": 0.1666, "angle": -99.94 },
					{ "time": 0.2333, "angle": -126.67 },
					{ "time": 0.3666, "angle": -143.06 },
					{ "time": 0.4, "angle": -127.91 },
					{ "time": 0.4333, "angle": -103.51 },
					{ "time": 0.4666, "angle": -78.45 },
					{ "time": 0.5, "angle": -17.83, "curve": "stepped" },
					{ "time": 0.6, "angle": -17.83 }
				]
			},
			"calf_right": {
				"rotate": [
					{ "time": 0, "angle": 77.11 },
					{ "time": 0.0333, "angle": 85.91 },
					{ "time": 0.0666, "angle": 0.99 },
					{ "time": 0.1666, "angle": -2.74 },
					{ "time": 0.2333, "angle": 50.54 },
					{ "time": 0.3666, "angle": 128.84 },
					{ "time": 0.4, "angle": 124.62 },
					{ "time": 0.4333, "angle": 100.47 },
					{ "time": 0.4666, "angle": 73.77 },
					{ "time": 0.5, "angle": -2.63, "curve": "stepped" },
					{ "time": 0.6, "angle": -2.63 }
				]
			},
			"leg_left": {
				"rotate": [
					{ "time": 0, "angle": -0.55 },
					{ "time": 0.0333, "angle": -0.66 },
					{ "time": 0.0666, "angle": -22.23 },
					{ "time": 0.1666, "angle": -96.48 },
					{ "time": 0.3, "angle": -90.22 },
					{ "time": 0.3333, "angle": -79.52 },
					{ "time": 0.3666, "angle": -105.87 },
					{ "time": 0.4, "angle": -87.86 },
					{ "time": 0.4333, "angle": -82.69 },
					{ "time": 0.4666, "angle": -67.05 },
					{ "time": 0.5, "angle": -19.23, "curve": "stepped" },
					{ "time": 0.6, "angle": -19.23 }
				],
				"translate": [
					{ "time": 0.3, "x": 0, "y": 0 }
				],
				"scale": [
					{ "time": 0.3, "x": 1, "y": 1 }
				]
			},
			"calf_left": {
				"rotate": [
					{ "time": 0, "angle": -3.35 },
					{ "time": 0.0333, "angle": 100.62 },
					{ "time": 0.0666, "angle": 85.11 },
					{ "time": 0.1666, "angle": 14.96 },
					{ "time": 0.3, "angle": 2.13 },
					{ "time": 0.3333, "angle": -1.9 },
					{ "time": 0.3666, "angle": 55.91 },
					{ "time": 0.4, "angle": 66.75 },
					{ "time": 0.4333, "angle": 63.62 },
					{ "time": 0.4666, "angle": 48.52 },
					{ "time": 0.5, "angle": -3.28, "curve": "stepped" },
					{ "time": 0.6, "angle": -3.28 }
				],
				"translate": [
					{ "time": 0.3, "x": 0, "y": 0 }
				],
				"scale": [
					{ "time": 0.3, "x": 1, "y": 1 }
				]
			},
			"foot_left": {
				"rotate": [
					{ "time": 0, "angle": -18.93, "curve": "stepped" },
					{ "time": 0.3, "angle": -18.93 },
					{ "time": 0.3333, "angle": 10.64 },
					{ "time": 0.5, "angle": 2.27, "curve": "stepped" },
					{ "time": 0.6, "angle": 2.27 }
				],
				"translate": [
					{ "time": 0, "x": -0.92, "y": -2.13, "curve": "stepped" },
					{ "time": 0.3, "x": -0.92, "y": -2.13 },
					{ "time": 0.3333, "x": -1.47, "y": 0.61 }
				],
				"scale": [
					{ "time": 0.3, "x": 1, "y": 1 }
				]
			},
			"foot_right": {
				"rotate": [
					{ "time": 0, "angle": -24.95 },
					{ "time": 0.0666, "angle": -6.25 },
					{ "time": 0.4, "angle": -15.3 },
					{ "time": 0.5, "angle": 2.98, "curve": "stepped" },
					{ "time": 0.6, "angle": 2.98 }
				]
			},
			"skirt": {
				"rotate": [
					{ "time": 0, "angle": -12.88 },
					{ "time": 0.0666, "angle": 56.18 },
					{ "time": 0.1666, "angle": -28.67 },
					{ "time": 0.5, "angle": -14.37, "curve": "stepped" },
					{ "time": 0.6, "angle": -14.37 }
				],
				"translate": [
					{ "time": 0, "x": -14.68, "y": -12.45 },
					{ "time": 0.0666, "x": -9.62, "y": -23.35 },
					{ "time": 0.1666, "x": -20.88, "y": 1.91 },
					{ "time": 0.5, "x": -18.14, "y": 3.75, "curve": "stepped" },
					{ "time": 0.6, "x": -18.14, "y": 3.75 }
				]
			},
			"body": {
				"rotate": [
					{ "time": 0, "angle": 6.61 },
					{ "time": 0.0666, "angle": -299.68 },
					{ "time": 0.1666, "angle": -8.19 },
					{ "time": 0.2333, "angle": 8.72, "curve": "stepped" },
					{ "time": 0.4, "angle": 8.72 },
					{ "time": 0.4666, "angle": 1.21 },
					{ "time": 0.5, "angle": -12.36, "curve": "stepped" },
					{ "time": 0.6, "angle": -12.36 }
				],
				"translate": [
					{ "time": 0, "x": -5.38, "y": -10.27 },
					{ "time": 0.0333, "x": -2.03, "y": -21.44 },
					{ "time": 0.1, "x": -7.22, "y": -13.96 },
					{ "time": 0.1666, "x": -20.84, "y": -8.85 },
					{ "time": 0.2333, "x": -12.71, "y": -25.25, "curve": "stepped" },
					{ "time": 0.4, "x": -12.71, "y": -25.25 },
					{ "time": 0.4666, "x": -18.51, "y": -12.98 },
					{ "time": 0.5, "x": -22.27, "y": -0.56, "curve": "stepped" },
					{ "time": 0.6, "x": -22.27, "y": -0.56 }
				],
				"scale": [
					{ "time": 0.4, "x": 1, "y": 1 }
				]
			},
			"head": {
				"rotate": [
					{ "time": 0, "angle": 10.49 },
					{ "time": 0.1666, "angle": 19.89 },
					{ "time": 0.2333, "angle": 30.72, "curve": "stepped" },
					{ "time": 0.3, "angle": 30.72, "curve": "stepped" },
					{ "time": 0.3666, "angle": 30.72 },
					{ "time": 0.4666, "angle": 14.14 }
				],
				"translate": [
					{ "time": 0.2333, "x": -2.62, "y": 2.81, "curve": "stepped" },
					{ "time": 0.3, "x": -2.62, "y": 2.81, "curve": "stepped" },
					{ "time": 0.3666, "x": -2.62, "y": 2.81 }
				],
				"scale": [
					{ "time": 0.3666, "x": 1, "y": 1 }
				]
			},
			"hair": {
				"rotate": [
					{ "time": 0, "angle": -11.15 },
					{ "time": 0.1666, "angle": 10.48 }
				]
			}
		},
		"slots": {
			"head": {
				"attachment": [
					{ "time": 0, "name": "boss_skin/head" },
					{ "time": 0.0666, "name": "boss_skin/faces/attack" },
					{ "time": 0.5, "name": "boss_skin/head" }
				]
			},
			"weapon": {
				"attachment": [
					{ "time": 0, "name": "boss_skin/weapon" }
				]
			}
		},
		"draworder": [
			{
				"time": 0.1333,
				"offsets": [
					{ "slot": "head", "offset": 3 },
					{ "slot": "pony", "offset": 3 }
				]
			},
			{
				"time": 0.1666,
				"offsets": [
					{ "slot": "weapon", "offset": 6 },
					{ "slot": "skirt", "offset": -2 }
				]
			},
			{
				"time": 0.3666,
				"offsets": [
					{ "slot": "skirt", "offset": -2 }
				]
			}
		]
	},
	"die": {
		"bones": {
			"root": {
				"rotate": [
					{ "time": 0, "angle": 0 }
				],
				"translate": [
					{ "time": 0, "x": 0, "y": 0 }
				],
				"scale": [
					{ "time": 0, "x": 1, "y": 1 }
				]
			},
			"hip": {
				"rotate": [
					{ "time": 0, "angle": 0 }
				],
				"translate": [
					{ "time": 0, "x": 0, "y": 0 },
					{ "time": 0.1, "x": -10.13, "y": -82.05 },
					{ "time": 0.4666, "x": -8.65, "y": -103.74, "curve": "stepped" },
					{ "time": 0.6666, "x": -8.65, "y": -103.74 }
				],
				"scale": [
					{ "time": 0, "x": 1, "y": 1 }
				]
			},
			"body": {
				"rotate": [
					{ "time": 0, "angle": 0 },
					{ "time": 0.2, "angle": -302.23 },
					{ "time": 0.3333, "angle": -288.84 },
					{ "time": 0.4666, "angle": -275.27, "curve": "stepped" },
					{ "time": 0.6666, "angle": -275.27 }
				],
				"translate": [
					{ "time": 0, "x": 0, "y": 0 },
					{ "time": 0.2, "x": 24.23, "y": -2.79 },
					{ "time": 0.3333, "x": 25.18, "y": -4.85 },
					{ "time": 0.4666, "x": 33.22, "y": -7.13, "curve": "stepped" },
					{ "time": 0.6666, "x": 33.22, "y": -7.13 }
				],
				"scale": [
					{ "time": 0, "x": 1, "y": 1 }
				]
			},
			"leg_left": {
				"rotate": [
					{ "time": 0, "angle": 0 },
					{ "time": 0.1, "angle": -0.24 },
					{ "time": 0.3333, "angle": 51.64 }
				],
				"translate": [
					{ "time": 0, "x": 0, "y": 0 }
				],
				"scale": [
					{ "time": 0, "x": 1, "y": 1 }
				]
			},
			"leg_right": {
				"rotate": [
					{ "time": 0, "angle": 0 },
					{ "time": 0.1, "angle": 1.95 },
					{ "time": 0.3333, "angle": 9.34 },
					{ "time": 0.4666, "angle": 29.26, "curve": "stepped" },
					{ "time": 0.6666, "angle": 29.26 }
				],
				"translate": [
					{ "time": 0, "x": 0, "y": 0 }
				],
				"scale": [
					{ "time": 0, "x": 1, "y": 1 }
				]
			},
			"skirt": {
				"rotate": [
					{ "time": 0, "angle": 0 },
					{ "time": 0.2, "angle": 22 },
					{ "time": 0.4666, "angle": 39.57, "curve": "stepped" },
					{ "time": 0.6666, "angle": 39.57 }
				],
				"translate": [
					{ "time": 0, "x": 0, "y": 0 },
					{ "time": 0.2, "x": -4.05, "y": 0.12 },
					{ "time": 0.4666, "x": -5.22, "y": -4.9, "curve": "stepped" },
					{ "time": 0.6666, "x": -5.22, "y": -4.9 }
				],
				"scale": [
					{ "time": 0, "x": 1, "y": 1 }
				]
			},
			"calf_left": {
				"rotate": [
					{ "time": 0, "angle": 0 },
					{ "time": 0.1, "angle": 96.11 },
					{ "time": 0.3333, "angle": 22.66 }
				],
				"translate": [
					{ "time": 0, "x": 0, "y": 0 }
				],
				"scale": [
					{ "time": 0, "x": 1, "y": 1 }
				]
			},
			"calf_right": {
				"rotate": [
					{ "time": 0, "angle": 0 },
					{ "time": 0.1, "angle": 96.11 },
					{ "time": 0.3333, "angle": 92.6 },
					{ "time": 0.4666, "angle": 85.44, "curve": "stepped" },
					{ "time": 0.6666, "angle": 85.44 }
				],
				"translate": [
					{ "time": 0, "x": 0, "y": 0 }
				],
				"scale": [
					{ "time": 0, "x": 1, "y": 1 }
				]
			},
			"head": {
				"rotate": [
					{ "time": 0, "angle": 0 },
					{ "time": 0.2, "angle": -16.05 },
					{ "time": 0.3333, "angle": -3.4 },
					{ "time": 0.4666, "angle": 8.46, "curve": "stepped" },
					{ "time": 0.6666, "angle": 8.46 }
				],
				"translate": [
					{ "time": 0, "x": 0, "y": 0 }
				],
				"scale": [
					{ "time": 0, "x": 1, "y": 1 }
				]
			},
			"left_shoulder": {
				"rotate": [
					{ "time": 0, "angle": 0 },
					{ "time": 0.2, "angle": 315.95 },
					{ "time": 0.3333, "angle": 173.01 },
					{ "time": 0.4666, "angle": 275.76, "curve": "stepped" },
					{ "time": 0.6666, "angle": 275.76 }
				],
				"translate": [
					{ "time": 0, "x": 0, "y": 0 }
				],
				"scale": [
					{ "time": 0, "x": 1, "y": 1 }
				]
			},
			"right_shoulder": {
				"rotate": [
					{ "time": 0, "angle": 0 },
					{ "time": 0.2, "angle": -28.07 },
					{ "time": 0.3333, "angle": -86.87 },
					{ "time": 0.4666, "angle": -150.23, "curve": "stepped" },
					{ "time": 0.6666, "angle": -150.23 }
				],
				"translate": [
					{ "time": 0, "x": 0, "y": 0 }
				],
				"scale": [
					{ "time": 0, "x": 1, "y": 1 }
				]
			},
			"foot_left": {
				"rotate": [
					{ "time": 0, "angle": 0 },
					{ "time": 0.1, "angle": 21.64 }
				],
				"translate": [
					{ "time": 0, "x": 0, "y": 0 }
				],
				"scale": [
					{ "time": 0, "x": 1, "y": 1 }
				]
			},
			"foot_right": {
				"rotate": [
					{ "time": 0, "angle": 0 }
				],
				"translate": [
					{ "time": 0, "x": 0, "y": 0 }
				],
				"scale": [
					{ "time": 0, "x": 1, "y": 1 }
				]
			},
			"hair": {
				"rotate": [
					{ "time": 0, "angle": 0 }
				],
				"translate": [
					{ "time": 0, "x": 0, "y": 0 }
				],
				"scale": [
					{ "time": 0, "x": 1, "y": 1 }
				]
			},
			"left_arm": {
				"rotate": [
					{ "time": 0, "angle": 0 },
					{ "time": 0.2, "angle": -83.43 },
					{ "time": 0.3333, "angle": -25.71 },
					{ "time": 0.4666, "angle": 5.6, "curve": "stepped" },
					{ "time": 0.6666, "angle": 5.6 }
				],
				"translate": [
					{ "time": 0, "x": 0, "y": 0 }
				],
				"scale": [
					{ "time": 0, "x": 1, "y": 1 }
				]
			},
			"pony": {
				"rotate": [
					{ "time": 0, "angle": 0 }
				],
				"translate": [
					{ "time": 0, "x": 0, "y": 0 }
				],
				"scale": [
					{ "time": 0, "x": 1, "y": 1 }
				]
			},
			"right_arm": {
				"rotate": [
					{ "time": 0, "angle": 0 },
					{ "time": 0.2, "angle": -75.95 },
					{ "time": 0.3333, "angle": -49.58 },
					{ "time": 0.4666, "angle": -3.77, "curve": "stepped" },
					{ "time": 0.6666, "angle": -3.77 }
				],
				"translate": [
					{ "time": 0, "x": 0, "y": 0 }
				],
				"scale": [
					{ "time": 0, "x": 1, "y": 1 }
				]
			},
			"left_hand": {
				"rotate": [
					{ "time": 0, "angle": 0 }
				],
				"translate": [
					{ "time": 0, "x": 0, "y": 0 }
				],
				"scale": [
					{ "time": 0, "x": 1, "y": 1 }
				]
			},
			"right_hand": {
				"rotate": [
					{ "time": 0, "angle": 0 }
				],
				"translate": [
					{ "time": 0, "x": 0, "y": 0 }
				],
				"scale": [
					{ "time": 0, "x": 1, "y": 1 }
				]
			}
		},
		"slots": {
			"head": {
				"attachment": [
					{ "time": 0, "name": "boss_skin/faces/attack" }
				]
			},
			"weapon": {
				"attachment": [
					{ "time": 0, "name": "boss_skin/hand_right" }
				]
			}
		},
		"draworder": [
			{ "time": 0.2 },
			{ "time": 0.3333 }
		]
	},
	"hit": {
		"bones": {
			"leg_right": {
				"rotate": [
					{ "time": 0, "angle": -3.43, "curve": "stepped" },
					{ "time": 0.5, "angle": -3.43 }
				],
				"translate": [
					{ "time": 0, "x": 0, "y": 0, "curve": "stepped" },
					{ "time": 0.5, "x": 0, "y": 0 }
				]
			},
			"calf_right": {
				"rotate": [
					{ "time": 0, "angle": 101.89, "curve": "stepped" },
					{ "time": 0.5, "angle": 101.89 }
				],
				"translate": [
					{ "time": 0, "x": 0, "y": 0, "curve": "stepped" },
					{ "time": 0.5, "x": 0, "y": 0 }
				]
			},
			"leg_left": {
				"rotate": [
					{ "time": 0, "angle": -1.27, "curve": "stepped" },
					{ "time": 0.5, "angle": -1.27 }
				],
				"translate": [
					{ "time": 0, "x": 0, "y": 0, "curve": "stepped" },
					{ "time": 0.5, "x": 0, "y": 0 }
				]
			},
			"calf_left": {
				"rotate": [
					{ "time": 0, "angle": 87.04, "curve": "stepped" },
					{ "time": 0.5, "angle": 87.04 }
				],
				"translate": [
					{ "time": 0, "x": 0, "y": 0, "curve": "stepped" },
					{ "time": 0.5, "x": 0, "y": 0 }
				]
			},
			"foot_left": {
				"rotate": [
					{ "time": 0, "angle": 14.8, "curve": "stepped" },
					{ "time": 0.5, "angle": 14.8 }
				],
				"translate": [
					{ "time": 0, "x": 0, "y": 0, "curve": "stepped" },
					{ "time": 0.5, "x": 0, "y": 0 }
				]
			},
			"skirt": {
				"rotate": [
					{ "time": 0, "angle": 14.76, "curve": "stepped" },
					{ "time": 0.5, "angle": 14.76 }
				],
				"translate": [
					{ "time": 0, "x": -11.17, "y": -21.77, "curve": "stepped" },
					{ "time": 0.5, "x": -11.17, "y": -21.77 }
				]
			},
			"body": {
				"rotate": [
					{ "time": 0, "angle": 13.67 },
					{ "time": 0.0666, "angle": -344.08 },
					{ "time": 0.1666, "angle": -348.78 },
					{ "time": 0.3, "angle": -346.05 },
					{ "time": 0.4, "angle": 9.6 },
					{ "time": 0.5, "angle": 13.67 }
				],
				"translate": [
					{ "time": 0, "x": -2.82, "y": -27.39, "curve": "stepped" },
					{ "time": 0.5, "x": -2.82, "y": -27.39 }
				]
			},
			"right_shoulder": {
				"rotate": [
					{ "time": 0, "angle": 60.19, "curve": "stepped" },
					{ "time": 0.5, "angle": 60.19 }
				],
				"translate": [
					{ "time": 0, "x": 0, "y": 0, "curve": "stepped" },
					{ "time": 0.5, "x": 0, "y": 0 }
				]
			},
			"right_arm": {
				"rotate": [
					{ "time": 0, "angle": -38.03, "curve": "stepped" },
					{ "time": 0.5, "angle": -38.03 }
				],
				"translate": [
					{ "time": 0, "x": 0, "y": 0, "curve": "stepped" },
					{ "time": 0.5, "x": 0, "y": 0 }
				]
			},
			"left_shoulder": {
				"rotate": [
					{ "time": 0, "angle": 15.45 },
					{ "time": 0.0666, "angle": 7.68 },
					{ "time": 0.1666, "angle": -4.72 },
					{ "time": 0.3, "angle": 9.03 },
					{ "time": 0.4333, "angle": 10.97 },
					{ "time": 0.5, "angle": 15.45 }
				],
				"translate": [
					{ "time": 0, "x": 0, "y": 0, "curve": "stepped" },
					{ "time": 0.5, "x": 0, "y": 0 }
				]
			},
			"left_arm": {
				"rotate": [
					{ "time": 0, "angle": -62.71 },
					{ "time": 0.0666, "angle": -48.34 },
					{ "time": 0.1666, "angle": -32.71 },
					{ "time": 0.3, "angle": -62.79 },
					{ "time": 0.4333, "angle": -48.41 },
					{ "time": 0.5, "angle": -62.71 }
				],
				"translate": [
					{ "time": 0, "x": 0, "y": 0, "curve": "stepped" },
					{ "time": 0.5, "x": 0, "y": 0 }
				]
			},
			"head": {
				"rotate": [
					{ "time": 0, "angle": 25.92 },
					{ "time": 0.2333, "angle": 34.37 },
					{ "time": 0.5, "angle": 25.92 }
				],
				"translate": [
					{ "time": 0, "x": 0, "y": 0, "curve": "stepped" },
					{ "time": 0.5, "x": 0, "y": 0 }
				]
			},
			"hip": {
				"rotate": [
					{ "time": 0, "angle": 0, "curve": "stepped" },
					{ "time": 0.5, "angle": 0 }
				],
				"translate": [
					{ "time": 0, "x": 0, "y": -67.68, "curve": "stepped" },
					{ "time": 0.5, "x": 0, "y": -67.68 }
				]
			},
			"foot_right": {
				"rotate": [
					{ "time": 0, "angle": -9.41, "curve": "stepped" },
					{ "time": 0.5, "angle": -9.41 }
				],
				"translate": [
					{ "time": 0, "x": 0, "y": 0, "curve": "stepped" },
					{ "time": 0.5, "x": 0, "y": 0 }
				]
			},
			"root": {
				"rotate": [
					{ "time": 0, "angle": 0, "curve": "stepped" },
					{ "time": 0.5, "angle": 0 }
				],
				"translate": [
					{ "time": 0, "x": 0, "y": 0, "curve": "stepped" },
					{ "time": 0.5, "x": 0, "y": 0 }
				]
			},
			"hair": {
				"rotate": [
					{ "time": 0, "angle": 0 },
					{ "time": 0.1333, "angle": 6.72 },
					{ "time": 0.3666, "angle": 1.22 },
					{ "time": 0.5, "angle": 0 }
				],
				"translate": [
					{ "time": 0, "x": 0, "y": 0, "curve": "stepped" },
					{ "time": 0.5, "x": 0, "y": 0 }
				]
			},
			"pony": {
				"rotate": [
					{ "time": 0, "angle": 0, "curve": "stepped" },
					{ "time": 0.5, "angle": 0 }
				],
				"translate": [
					{ "time": 0, "x": 0, "y": 0, "curve": "stepped" },
					{ "time": 0.5, "x": 0, "y": 0 }
				]
			},
			"left_hand": {
				"rotate": [
					{ "time": 0, "angle": 0, "curve": "stepped" },
					{ "time": 0.5, "angle": 0 }
				],
				"translate": [
					{ "time": 0, "x": 0, "y": 0, "curve": "stepped" },
					{ "time": 0.5, "x": 0, "y": 0 }
				]
			},
			"right_hand": {
				"rotate": [
					{ "time": 0, "angle": 0, "curve": "stepped" },
					{ "time": 0.5, "angle": 0 }
				],
				"translate": [
					{ "time": 0, "x": 0, "y": 0, "curve": "stepped" },
					{ "time": 0.5, "x": 0, "y": 0 }
				]
			}
		},
		"slots": {
			"head": {
				"attachment": [
					{ "time": 0, "name": "boss_skin/faces/hit" }
				]
			},
			"weapon": {
				"attachment": [
					{ "time": 0, "name": "boss_skin/weapon" }
				]
			}
		}
	},
	"idle": {
		"bones": {
			"head": {
				"rotate": [
					{ "time": 0, "angle": 23.13, "curve": "stepped" },
					{ "time": 1.6, "angle": 23.13 }
				],
				"translate": [
					{ "time": 0, "x": 0, "y": 0, "curve": "stepped" },
					{ "time": 1.6, "x": 0, "y": 0 }
				],
				"scale": [
					{ "time": 0, "x": 1, "y": 1, "curve": "stepped" },
					{ "time": 1.6, "x": 1, "y": 1 }
				]
			},
			"right_shoulder": {
				"rotate": [
					{ "time": 0, "angle": -3.84 },
					{ "time": 1.2333, "angle": -14.07 },
					{ "time": 1.6, "angle": -3.84 }
				],
				"translate": [
					{ "time": 0, "x": 0, "y": 0, "curve": "stepped" },
					{ "time": 1.6, "x": 0, "y": 0 }
				],
				"scale": [
					{ "time": 0, "x": 1, "y": 1, "curve": "stepped" },
					{ "time": 1.6, "x": 1, "y": 1 }
				]
			},
			"right_arm": {
				"rotate": [
					{ "time": 0, "angle": -130.82 },
					{ "time": 1.2333, "angle": -130.29 },
					{ "time": 1.6, "angle": -130.82 }
				],
				"translate": [
					{ "time": 0, "x": 0, "y": 0, "curve": "stepped" },
					{ "time": 1.6, "x": 0, "y": 0 }
				],
				"scale": [
					{ "time": 0, "x": 1, "y": 1, "curve": "stepped" },
					{ "time": 1.6, "x": 1, "y": 1 }
				]
			},
			"left_shoulder": {
				"rotate": [
					{ "time": 0, "angle": 18.4 },
					{ "time": 0.5, "angle": 16.49 },
					{ "time": 1.0666, "angle": 15.35 },
					{ "time": 1.6, "angle": 18.4 }
				],
				"translate": [
					{ "time": 0, "x": 0, "y": 0, "curve": "stepped" },
					{ "time": 1.6, "x": 0, "y": 0 }
				],
				"scale": [
					{ "time": 0, "x": 1, "y": 1, "curve": "stepped" },
					{ "time": 1.6, "x": 1, "y": 1 }
				]
			},
			"left_arm": {
				"rotate": [
					{ "time": 0, "angle": -73.95 },
					{ "time": 0.5, "angle": -66.88 },
					{ "time": 1.0666, "angle": -57.87 },
					{ "time": 1.6, "angle": -73.95 }
				],
				"translate": [
					{ "time": 0, "x": 0, "y": 0, "curve": "stepped" },
					{ "time": 1.6, "x": 0, "y": 0 }
				],
				"scale": [
					{ "time": 0, "x": 1, "y": 1, "curve": "stepped" },
					{ "time": 1.6, "x": 1, "y": 1 }
				]
			},
			"root": {
				"rotate": [
					{ "time": 0, "angle": 0, "curve": "stepped" },
					{ "time": 1.6, "angle": 0 }
				],
				"translate": [
					{ "time": 0, "x": 0, "y": 0, "curve": "stepped" },
					{ "time": 1.6, "x": 0, "y": 0 }
				],
				"scale": [
					{ "time": 0, "x": 1, "y": 1, "curve": "stepped" },
					{ "time": 1.6, "x": 1, "y": 1 }
				]
			},
			"hip": {
				"rotate": [
					{ "time": 0, "angle": 0, "curve": "stepped" },
					{ "time": 1.6, "angle": 0 }
				],
				"translate": [
					{ "time": 0, "x": 0, "y": 0, "curve": "stepped" },
					{ "time": 1.6, "x": 0, "y": 0 }
				],
				"scale": [
					{ "time": 0, "x": 1, "y": 1, "curve": "stepped" },
					{ "time": 1.6, "x": 1, "y": 1 }
				]
			},
			"body": {
				"rotate": [
					{ "time": 0, "angle": 0, "curve": "stepped" },
					{ "time": 1.6, "angle": 0 }
				],
				"translate": [
					{ "time": 0, "x": 1, "y": -0.03 },
					{ "time": 0.8, "x": 5.5, "y": -0.17 },
					{ "time": 1.6, "x": 0, "y": 0 }
				],
				"scale": [
					{ "time": 0, "x": 1, "y": 1, "curve": "stepped" },
					{ "time": 1.6, "x": 1, "y": 1 }
				]
			},
			"leg_left": {
				"rotate": [
					{ "time": 0, "angle": 0, "curve": "stepped" },
					{ "time": 1.6, "angle": 0 }
				],
				"translate": [
					{ "time": 0, "x": 0, "y": 0, "curve": "stepped" },
					{ "time": 1.6, "x": 0, "y": 0 }
				],
				"scale": [
					{ "time": 0, "x": 1, "y": 1, "curve": "stepped" },
					{ "time": 1.6, "x": 1, "y": 1 }
				]
			},
			"leg_right": {
				"rotate": [
					{ "time": 0, "angle": 0, "curve": "stepped" },
					{ "time": 1.6, "angle": 0 }
				],
				"translate": [
					{ "time": 0, "x": 0, "y": 0, "curve": "stepped" },
					{ "time": 1.6, "x": 0, "y": 0 }
				],
				"scale": [
					{ "time": 0, "x": 1, "y": 1, "curve": "stepped" },
					{ "time": 1.6, "x": 1, "y": 1 }
				]
			},
			"skirt": {
				"rotate": [
					{ "time": 0, "angle": 0 },
					{ "time": 0.1666, "angle": 4.09 },
					{ "time": 0.5333, "angle": -2.47 },
					{ "time": 0.8666, "angle": 2.4 },
					{ "time": 1.3, "angle": -4.51 },
					{ "time": 1.6, "angle": 0 }
				],
				"translate": [
					{ "time": 0, "x": 0, "y": 0, "curve": "stepped" },
					{ "time": 1.6, "x": 0, "y": 0 }
				],
				"scale": [
					{ "time": 0, "x": 1, "y": 1, "curve": "stepped" },
					{ "time": 1.6, "x": 1, "y": 1 }
				]
			},
			"calf_left": {
				"rotate": [
					{ "time": 0, "angle": 0, "curve": "stepped" },
					{ "time": 1.6, "angle": 0 }
				],
				"translate": [
					{ "time": 0, "x": 0, "y": 0, "curve": "stepped" },
					{ "time": 1.6, "x": 0, "y": 0 }
				],
				"scale": [
					{ "time": 0, "x": 1, "y": 1, "curve": "stepped" },
					{ "time": 1.6, "x": 1, "y": 1 }
				]
			},
			"calf_right": {
				"rotate": [
					{ "time": 0, "angle": 0, "curve": "stepped" },
					{ "time": 1.6, "angle": 0 }
				],
				"translate": [
					{ "time": 0, "x": 0, "y": 0, "curve": "stepped" },
					{ "time": 1.6, "x": 0, "y": 0 }
				],
				"scale": [
					{ "time": 0, "x": 1, "y": 1, "curve": "stepped" },
					{ "time": 1.6, "x": 1, "y": 1 }
				]
			},
			"foot_left": {
				"rotate": [
					{ "time": 0, "angle": 0, "curve": "stepped" },
					{ "time": 1.6, "angle": 0 }
				],
				"translate": [
					{ "time": 0, "x": 0, "y": 0, "curve": "stepped" },
					{ "time": 1.6, "x": 0, "y": 0 }
				],
				"scale": [
					{ "time": 0, "x": 1, "y": 1, "curve": "stepped" },
					{ "time": 1.6, "x": 1, "y": 1 }
				]
			},
			"foot_right": {
				"rotate": [
					{ "time": 0, "angle": 0, "curve": "stepped" },
					{ "time": 1.6, "angle": 0 }
				],
				"translate": [
					{ "time": 0, "x": 0, "y": 0, "curve": "stepped" },
					{ "time": 1.6, "x": 0, "y": 0 }
				],
				"scale": [
					{ "time": 0, "x": 1, "y": 1, "curve": "stepped" },
					{ "time": 1.6, "x": 1, "y": 1 }
				]
			},
			"hair": {
				"rotate": [
					{ "time": 0, "angle": 0 },
					{ "time": 0.2333, "angle": 10.08 },
					{ "time": 0.5333, "angle": 18.23 },
					{ "time": 0.8666, "angle": 21.64 },
					{ "time": 1.1333, "angle": 21 },
					{ "time": 1.6, "angle": 0 }
				],
				"translate": [
					{ "time": 0, "x": 0, "y": 0, "curve": "stepped" },
					{ "time": 1.6, "x": 0, "y": 0 }
				],
				"scale": [
					{ "time": 0, "x": 1, "y": 1, "curve": "stepped" },
					{ "time": 1.6, "x": 1, "y": 1 }
				]
			},
			"pony": {
				"rotate": [
					{ "time": 0, "angle": 0, "curve": "stepped" },
					{ "time": 1.6, "angle": 0 }
				],
				"translate": [
					{ "time": 0, "x": 0, "y": 0, "curve": "stepped" },
					{ "time": 1.6, "x": 0, "y": 0 }
				],
				"scale": [
					{ "time": 0, "x": 1, "y": 1, "curve": "stepped" },
					{ "time": 1.6, "x": 1, "y": 1 }
				]
			},
			"left_hand": {
				"rotate": [
					{ "time": 0, "angle": 0, "curve": "stepped" },
					{ "time": 1.6, "angle": 0 }
				],
				"translate": [
					{ "time": 0, "x": 0, "y": 0, "curve": "stepped" },
					{ "time": 1.6, "x": 0, "y": 0 }
				],
				"scale": [
					{ "time": 0, "x": 1, "y": 1, "curve": "stepped" },
					{ "time": 1.6, "x": 1, "y": 1 }
				]
			},
			"right_hand": {
				"rotate": [
					{ "time": 0, "angle": 0, "curve": "stepped" },
					{ "time": 1.6, "angle": 0 }
				],
				"translate": [
					{ "time": 0, "x": 0, "y": 0, "curve": "stepped" },
					{ "time": 1.6, "x": 0, "y": 0 }
				],
				"scale": [
					{ "time": 0, "x": 1, "y": 1, "curve": "stepped" },
					{ "time": 1.6, "x": 1, "y": 1 }
				]
			}
		},
		"slots": {
			"weapon": {
				"attachment": [
					{ "time": 0, "name": "boss_skin/weapon" }
				]
			}
		}
	},
	"jump": {
		"bones": {
			"leg_right": {
				"rotate": [
					{ "time": 0, "angle": -76.62 },
					{ "time": 0.2, "angle": 0.19 },
					{ "time": 0.4, "angle": -56.17 },
					{ "time": 0.8, "angle": -24.22 },
					{ "time": 1, "angle": -15.36 },
					{ "time": 1.2, "angle": 9.7 }
				],
				"translate": [
					{ "time": 0, "x": 0, "y": 0, "curve": "stepped" },
					{ "time": 1.2, "x": 0, "y": 0 }
				],
				"scale": [
					{ "time": 0, "x": 1, "y": 1, "curve": "stepped" },
					{ "time": 1.2, "x": 1, "y": 1 }
				]
			},
			"calf_right": {
				"rotate": [
					{ "time": 0, "angle": 89.47 },
					{ "time": 0.2, "angle": -1.63 },
					{ "time": 0.4, "angle": 119.66 },
					{ "time": 0.8, "angle": 82.28 },
					{ "time": 1, "angle": 56.54 },
					{ "time": 1.2, "angle": -2.89 }
				],
				"translate": [
					{ "time": 0, "x": 0, "y": 0, "curve": "stepped" },
					{ "time": 1.2, "x": 0, "y": 0 }
				],
				"scale": [
					{ "time": 0, "x": 1, "y": 1, "curve": "stepped" },
					{ "time": 1.2, "x": 1, "y": 1 }
				]
			},
			"foot_right": {
				"rotate": [
					{ "time": 0, "angle": -24.48 },
					{ "time": 0.2, "angle": -4.94 },
					{ "time": 1, "angle": 4.7, "curve": "stepped" },
					{ "time": 1.2, "angle": 4.7 }
				],
				"translate": [
					{ "time": 0, "x": -1.06, "y": -1.64 },
					{ "time": 0.2, "x": 0.18, "y": -0.4, "curve": "stepped" },
					{ "time": 1.2, "x": 0.18, "y": -0.4 }
				],
				"scale": [
					{ "time": 0, "x": 1, "y": 1, "curve": "stepped" },
					{ "time": 1.2, "x": 1, "y": 1 }
				]
			},
			"leg_left": {
				"rotate": [
					{ "time": 0, "angle": -63.96 },
					{ "time": 0.2, "angle": -1.73 },
					{ "time": 0.4, "angle": -63.05 },
					{ "time": 0.6, "angle": -22.5 },
					{ "time": 0.8, "angle": -43.05 },
					{ "time": 1, "angle": -9.3 },
					{ "time": 1.2, "angle": 9.21 }
				],
				"translate": [
					{ "time": 0, "x": 0, "y": 0, "curve": "stepped" },
					{ "time": 1.2, "x": 0, "y": 0 }
				],
				"scale": [
					{ "time": 0, "x": 1, "y": 1, "curve": "stepped" },
					{ "time": 1.2, "x": 1, "y": 1 }
				]
			},
			"calf_left": {
				"rotate": [
					{ "time": 0, "angle": 78.19 },
					{ "time": 0.2, "angle": -3.76 },
					{ "time": 0.4, "angle": 65.62 },
					{ "time": 0.6, "angle": 19.31 },
					{ "time": 0.8, "angle": 67.57 },
					{ "time": 1, "angle": 26.6 },
					{ "time": 1.2, "angle": -3.74 }
				],
				"translate": [
					{ "time": 0, "x": 0, "y": 0, "curve": "stepped" },
					{ "time": 1.2, "x": 0, "y": 0 }
				],
				"scale": [
					{ "time": 0, "x": 1, "y": 1, "curve": "stepped" },
					{ "time": 1.2, "x": 1, "y": 1 }
				]
			},
			"foot_left": {
				"rotate": [
					{ "time": 0, "angle": -29.83 },
					{ "time": 0.2, "angle": 5.74 },
					{ "time": 0.8, "angle": -17.98 },
					{ "time": 1, "angle": -9.92 },
					{ "time": 1.2, "angle": 1.18 }
				],
				"translate": [
					{ "time": 0, "x": -2.31, "y": -3.17 },
					{ "time": 0.2, "x": -1.33, "y": 0.16 },
					{ "time": 0.8, "x": -1.64, "y": -0.63, "curve": "stepped" },
					{ "time": 1.2, "x": -1.64, "y": -0.63 }
				],
				"scale": [
					{ "time": 0, "x": 1, "y": 1, "curve": "stepped" },
					{ "time": 1.2, "x": 1, "y": 1 }
				]
			},
			"hip": {
				"rotate": [
					{ "time": 0, "angle": 17.44 },
					{ "time": 0.2, "angle": 19.28 },
					{ "time": 0.4, "angle": -24.22 },
					{ "time": 0.6, "angle": -22.41 },
					{ "time": 0.8, "angle": -8, "curve": "stepped" },
					{ "time": 1.2, "angle": -8 }
				],
				"translate": [
					{ "time": 0, "x": 0, "y": -30.01 },
					{ "time": 0.2, "x": 0, "y": -0.76 },
					{ "time": 0.8, "x": 0, "y": -14.32 },
					{ "time": 1, "x": 0, "y": 8.87 },
					{ "time": 1.2, "x": 0, "y": 14.88 }
				],
				"scale": [
					{ "time": 0, "x": 1, "y": 1, "curve": "stepped" },
					{ "time": 1.2, "x": 1, "y": 1 }
				]
			},
			"body": {
				"rotate": [
					{ "time": 0, "angle": 10.13, "curve": "stepped" },
					{ "time": 1.2, "angle": 10.13 }
				],
				"translate": [
					{ "time": 0, "x": 0, "y": 0, "curve": "stepped" },
					{ "time": 1.2, "x": 0, "y": 0 }
				],
				"scale": [
					{ "time": 0, "x": 1, "y": 1, "curve": "stepped" },
					{ "time": 1.2, "x": 1, "y": 1 }
				]
			},
			"skirt": {
				"rotate": [
					{ "time": 0, "angle": -3.28, "curve": "stepped" },
					{ "time": 1.2, "angle": -3.28 }
				],
				"translate": [
					{ "time": 0, "x": -14.33, "y": -18.21, "curve": "stepped" },
					{ "time": 1.2, "x": -14.33, "y": -18.21 }
				],
				"scale": [
					{ "time": 0, "x": 1, "y": 1, "curve": "stepped" },
					{ "time": 1.2, "x": 1, "y": 1 }
				]
			},
			"left_shoulder": {
				"rotate": [
					{ "time": 0, "angle": -32.98 },
					{ "time": 0.2, "angle": 6.13 },
					{ "time": 0.4, "angle": 322.62 },
					{ "time": 0.8, "angle": 15.7 },
					{ "time": 1.2, "angle": 6.87 }
				],
				"translate": [
					{ "time": 0, "x": 0, "y": 0, "curve": "stepped" },
					{ "time": 1.2, "x": 0, "y": 0 }
				],
				"scale": [
					{ "time": 0, "x": 1, "y": 1, "curve": "stepped" },
					{ "time": 1.2, "x": 1, "y": 1 }
				]
			},
			"left_arm": {
				"rotate": [
					{ "time": 0, "angle": -121.6 },
					{ "time": 0.2, "angle": -21.72 },
					{ "time": 0.4, "angle": -66.56 },
					{ "time": 0.8, "angle": -64.31 },
					{ "time": 1.2, "angle": -40.48 }
				],
				"translate": [
					{ "time": 0, "x": 0, "y": 0, "curve": "stepped" },
					{ "time": 1.2, "x": 0, "y": 0 }
				],
				"scale": [
					{ "time": 0, "x": 1, "y": 1, "curve": "stepped" },
					{ "time": 1.2, "x": 1, "y": 1 }
				]
			},
			"right_shoulder": {
				"rotate": [
					{ "time": 0, "angle": 106.72 },
					{ "time": 0.2, "angle": -253.27 },
					{ "time": 0.4, "angle": -288.78 },
					{ "time": 1.2, "angle": 31.94 }
				],
				"translate": [
					{ "time": 0, "x": 0, "y": 0, "curve": "stepped" },
					{ "time": 1.2, "x": 0, "y": 0 }
				],
				"scale": [
					{ "time": 0, "x": 1, "y": 1, "curve": "stepped" },
					{ "time": 1.2, "x": 1, "y": 1 }
				]
			},
			"right_arm": {
				"rotate": [
					{ "time": 0, "angle": 22.43, "curve": "stepped" },
					{ "time": 0.2, "angle": 22.43 },
					{ "time": 0.4, "angle": -85.86 },
					{ "time": 1.2, "angle": 0.64 }
				],
				"translate": [
					{ "time": 0, "x": 0, "y": 0, "curve": "stepped" },
					{ "time": 1.2, "x": 0, "y": 0 }
				],
				"scale": [
					{ "time": 0, "x": 1, "y": 1, "curve": "stepped" },
					{ "time": 1.2, "x": 1, "y": 1 }
				]
			},
			"head": {
				"rotate": [
					{ "time": 0, "angle": 0 },
					{ "time": 0.4, "angle": 24.87, "curve": "stepped" },
					{ "time": 1.2, "angle": 24.87 }
				],
				"translate": [
					{ "time": 0, "x": 0, "y": 0, "curve": "stepped" },
					{ "time": 1.2, "x": 0, "y": 0 }
				],
				"scale": [
					{ "time": 0, "x": 1, "y": 1, "curve": "stepped" },
					{ "time": 1.2, "x": 1, "y": 1 }
				]
			},
			"hair": {
				"rotate": [
					{ "time": 0, "angle": 0, "curve": "stepped" },
					{ "time": 0.2666, "angle": 0 },
					{ "time": 0.4, "angle": 135.9, "curve": "stepped" },
					{
						"time": 0.8,
						"angle": 135.9,
						"curve": [ 0, 0.94, 0.75, 1 ]
					},
					{ "time": 1.0666, "angle": -8.14 },
					{ "time": 1.2, "angle": 0 }
				],
				"translate": [
					{ "time": 0, "x": 0, "y": 0, "curve": "stepped" },
					{ "time": 0.2666, "x": 0, "y": 0 },
					{ "time": 0.4, "x": -93.48, "y": 27.32, "curve": "stepped" },
					{
						"time": 0.8,
						"x": -93.48,
						"y": 27.32,
						"curve": [ 0, 0.46, 0.409, 0.78 ]
					},
					{
						"time": 0.9333,
						"x": -7.81,
						"y": 6.7,
						"curve": [ 0.302, 0.92, 0.79, 1 ]
					},
					{ "time": 1.2, "x": 0, "y": 0 }
				],
				"scale": [
					{ "time": 0, "x": 1, "y": 1, "curve": "stepped" },
					{ "time": 0.2666, "x": 1, "y": 1, "curve": "stepped" },
					{ "time": 0.8, "x": 1, "y": 1, "curve": "stepped" },
					{ "time": 1.2, "x": 1, "y": 1 }
				]
			},
			"right_hand": {
				"rotate": [
					{ "time": 0, "angle": 0 },
					{ "time": 1.2, "angle": 5.28 }
				],
				"translate": [
					{ "time": 0, "x": 0, "y": 0, "curve": "stepped" },
					{ "time": 1.2, "x": 0, "y": 0 }
				],
				"scale": [
					{ "time": 0, "x": 1, "y": 1, "curve": "stepped" },
					{ "time": 1.2, "x": 1, "y": 1 }
				]
			},
			"root": {
				"rotate": [
					{ "time": 0, "angle": 0, "curve": "stepped" },
					{ "time": 1.2, "angle": 0 }
				],
				"translate": [
					{ "time": 0, "x": 0, "y": 0, "curve": "stepped" },
					{ "time": 1.2, "x": 0, "y": 0 }
				],
				"scale": [
					{ "time": 0, "x": 1, "y": 1, "curve": "stepped" },
					{ "time": 1.2, "x": 1, "y": 1 }
				]
			},
			"pony": {
				"rotate": [
					{ "time": 0, "angle": 0, "curve": "stepped" },
					{ "time": 1.2, "angle": 0 }
				],
				"translate": [
					{ "time": 0, "x": 0, "y": 0, "curve": "stepped" },
					{ "time": 1.2, "x": 0, "y": 0 }
				],
				"scale": [
					{ "time": 0, "x": 1, "y": 1, "curve": "stepped" },
					{ "time": 1.2, "x": 1, "y": 1 }
				]
			},
			"left_hand": {
				"rotate": [
					{ "time": 0, "angle": 0, "curve": "stepped" },
					{ "time": 1.2, "angle": 0 }
				],
				"translate": [
					{ "time": 0, "x": 0, "y": 0, "curve": "stepped" },
					{ "time": 1.2, "x": 0, "y": 0 }
				],
				"scale": [
					{ "time": 0, "x": 1, "y": 1, "curve": "stepped" },
					{ "time": 1.2, "x": 1, "y": 1 }
				]
			}
		},
		"slots": {
			"head": {
				"attachment": [
					{ "time": 0, "name": "boss_skin/head" },
					{ "time": 0.2, "name": "boss_skin/faces/jump" },
					{ "time": 1.1333, "name": "boss_skin/head" }
				]
			},
			"weapon": {
				"attachment": [
					{ "time": 0, "name": "boss_skin/weapon" }
				]
			}
		},
		"draworder": [
			{
				"time": 0,
				"offsets": [
					{ "slot": "head", "offset": 3 },
					{ "slot": "pony", "offset": 3 }
				]
			},
			{
				"time": 0.2,
				"offsets": [
					{ "slot": "head", "offset": 3 },
					{ "slot": "pony", "offset": 3 }
				]
			},
			{
				"time": 1.2,
				"offsets": [
					{ "slot": "head", "offset": 3 },
					{ "slot": "pony", "offset": 3 }
				]
			}
		]
	},
	"run": {
		"bones": {
			"root": {
				"rotate": [
					{ "time": 0, "angle": 0, "curve": "stepped" },
					{ "time": 0.8, "angle": 0, "curve": "stepped" },
					{ "time": 1.6, "angle": 0 }
				],
				"translate": [
					{ "time": 0, "x": 0, "y": 0, "curve": "stepped" },
					{ "time": 0.8, "x": 0, "y": 0, "curve": "stepped" },
					{ "time": 1.6, "x": 0, "y": 0 }
				],
				"scale": [
					{ "time": 0, "x": 1, "y": 1, "curve": "stepped" },
					{ "time": 0.8, "x": 1, "y": 1, "curve": "stepped" },
					{ "time": 1.6, "x": 1, "y": 1 }
				]
			},
			"body": {
				"rotate": [
					{ "time": 0, "angle": 5.8 },
					{ "time": 0.4, "angle": 1.7 },
					{ "time": 0.8, "angle": 5.8 },
					{ "time": 1.2, "angle": 1.7 },
					{ "time": 1.6, "angle": 5.8 }
				],
				"translate": [
					{ "time": 0, "x": 0, "y": 0, "curve": "stepped" },
					{ "time": 0.8, "x": 0, "y": 0, "curve": "stepped" },
					{ "time": 1.6, "x": 0, "y": 0 }
				],
				"scale": [
					{ "time": 0, "x": 1, "y": 1, "curve": "stepped" },
					{ "time": 0.8, "x": 1, "y": 1, "curve": "stepped" },
					{ "time": 1.6, "x": 1, "y": 1 }
				]
			},
			"leg_left": {
				"rotate": [
					{ "time": 0, "angle": -30.96 },
					{ "time": 0.0666, "angle": -38.19 },
					{ "time": 0.1, "angle": -37.52 },
					{ "time": 0.2, "angle": -5.38 },
					{ "time": 0.3, "angle": 2.92 },
					{ "time": 0.4, "angle": 12.13 },
					{ "time": 0.5, "angle": 6.84 },
					{ "time": 0.6, "angle": -39 },
					{ "time": 0.7, "angle": -73.8 },
					{ "time": 0.8, "angle": -30.96 },
					{ "time": 0.8666, "angle": -38.19 },
					{ "time": 0.9, "angle": -37.52 },
					{ "time": 1, "angle": -5.38 },
					{ "time": 1.1, "angle": 2.92 },
					{ "time": 1.2, "angle": 12.13 },
					{ "time": 1.3, "angle": 6.84 },
					{ "time": 1.4, "angle": -39 },
					{ "time": 1.5, "angle": -73.8 },
					{ "time": 1.6, "angle": -30.96 }
				],
				"translate": [
					{ "time": 0, "x": 0, "y": 0, "curve": "stepped" },
					{ "time": 0.8, "x": 0, "y": 0, "curve": "stepped" },
					{ "time": 1.6, "x": 0, "y": 0 }
				],
				"scale": [
					{ "time": 0, "x": 1, "y": 1, "curve": "stepped" },
					{ "time": 0.8, "x": 1, "y": 1, "curve": "stepped" },
					{ "time": 1.6, "x": 1, "y": 1 }
				]
			},
			"leg_right": {
				"rotate": [
					{ "time": 0, "angle": 12.91 },
					{ "time": 0.1, "angle": 27.62 },
					{ "time": 0.2, "angle": -3.13 },
					{ "time": 0.3, "angle": -29.58 },
					{ "time": 0.4, "angle": -27.31 },
					{ "time": 0.5, "angle": -35.32 },
					{ "time": 0.5333, "angle": -35.08 },
					{ "time": 0.6, "angle": -3.73 },
					{ "time": 0.7, "angle": 8.83 },
					{ "time": 0.8, "angle": 12.91 },
					{ "time": 0.9, "angle": 27.62 },
					{ "time": 1, "angle": -3.13 },
					{ "time": 1.1, "angle": -29.58 },
					{ "time": 1.2, "angle": -27.31 },
					{ "time": 1.3, "angle": -35.32 },
					{ "time": 1.3333, "angle": -35.08 },
					{ "time": 1.4, "angle": -3.73 },
					{ "time": 1.5, "angle": 8.83 },
					{ "time": 1.6, "angle": 12.91 }
				],
				"translate": [
					{ "time": 0, "x": 0, "y": 0, "curve": "stepped" },
					{ "time": 0.8, "x": 0, "y": 0, "curve": "stepped" },
					{ "time": 1.6, "x": 0, "y": 0 }
				],
				"scale": [
					{ "time": 0, "x": 1, "y": 1, "curve": "stepped" },
					{ "time": 0.8, "x": 1, "y": 1, "curve": "stepped" },
					{ "time": 1.6, "x": 1, "y": 1 }
				]
			},
			"skirt": {
				"rotate": [
					{ "time": 0, "angle": 6.37 },
					{ "time": 0.0666, "angle": 3.1 },
					{ "time": 0.1333, "angle": -0.76 },
					{ "time": 0.1666, "angle": 5.69 },
					{ "time": 0.2333, "angle": -1.31 },
					{ "time": 0.3333, "angle": -5.77 },
					{ "time": 0.5666, "angle": 0.82 },
					{ "time": 0.6, "angle": 6.21 },
					{ "time": 0.6666, "angle": -5.05 },
					{ "time": 0.7, "angle": 2.62 },
					{ "time": 0.8, "angle": 6.37 },
					{ "time": 0.8666, "angle": 3.1 },
					{ "time": 0.9333, "angle": -0.76 },
					{ "time": 0.9666, "angle": 5.69 },
					{ "time": 1.0333, "angle": -1.31 },
					{ "time": 1.1333, "angle": -5.77 },
					{ "time": 1.3666, "angle": 0.82 },
					{ "time": 1.4, "angle": 6.21 },
					{ "time": 1.4666, "angle": -5.05 },
					{ "time": 1.5, "angle": 2.62 },
					{ "time": 1.6, "angle": 6.37 }
				],
				"translate": [
					{ "time": 0, "x": 0, "y": 0, "curve": "stepped" },
					{ "time": 0.8, "x": 0, "y": 0, "curve": "stepped" },
					{ "time": 1.6, "x": 0, "y": 0 }
				],
				"scale": [
					{ "time": 0, "x": 1, "y": 1, "curve": "stepped" },
					{ "time": 0.8, "x": 1, "y": 1, "curve": "stepped" },
					{ "time": 1.6, "x": 1, "y": 1 }
				]
			},
			"calf_left": {
				"rotate": [
					{ "time": 0, "angle": -3.91 },
					{ "time": 0.0666, "angle": 14.78 },
					{ "time": 0.1, "angle": 26.07 },
					{ "time": 0.2, "angle": -2.44 },
					{ "time": 0.3, "angle": -4.1 },
					{ "time": 0.4, "angle": -7.42 },
					{ "time": 0.5, "angle": 27.38 },
					{ "time": 0.6, "angle": 70.89 },
					{ "time": 0.7, "angle": 86.7 },
					{ "time": 0.8, "angle": -3.91 },
					{ "time": 0.8666, "angle": 14.78 },
					{ "time": 0.9, "angle": 26.07 },
					{ "time": 1, "angle": -2.44 },
					{ "time": 1.1, "angle": -4.1 },
					{ "time": 1.2, "angle": -7.42 },
					{ "time": 1.3, "angle": 27.38 },
					{ "time": 1.4, "angle": 70.89 },
					{ "time": 1.5, "angle": 86.7 },
					{ "time": 1.6, "angle": -3.91 }
				],
				"translate": [
					{ "time": 0, "x": 0, "y": 0, "curve": "stepped" },
					{ "time": 0.8, "x": 0, "y": 0, "curve": "stepped" },
					{ "time": 1.6, "x": 0, "y": 0 }
				],
				"scale": [
					{ "time": 0, "x": 1, "y": 1, "curve": "stepped" },
					{ "time": 0.8, "x": 1, "y": 1, "curve": "stepped" },
					{ "time": 1.6, "x": 1, "y": 1 }
				]
			},
			"calf_right": {
				"rotate": [
					{ "time": 0, "angle": 28.7 },
					{ "time": 0.1, "angle": 10.54 },
					{ "time": 0.2, "angle": 42.14 },
					{ "time": 0.3, "angle": 50.88 },
					{ "time": 0.4, "angle": -2.49 },
					{ "time": 0.5, "angle": 24.58 },
					{ "time": 0.5333, "angle": 31.32 },
					{ "time": 0.6, "angle": -2.71 },
					{ "time": 0.7, "angle": -1.65 },
					{ "time": 0.8, "angle": 28.7 },
					{ "time": 0.9, "angle": 10.54 },
					{ "time": 1, "angle": 42.14 },
					{ "time": 1.1, "angle": 50.88 },
					{ "time": 1.2, "angle": -2.49 },
					{ "time": 1.3, "angle": 24.58 },
					{ "time": 1.3333, "angle": 31.32 },
					{ "time": 1.4, "angle": -2.71 },
					{ "time": 1.5, "angle": -1.65 },
					{ "time": 1.6, "angle": 28.7 }
				],
				"translate": [
					{ "time": 0, "x": 0, "y": 0, "curve": "stepped" },
					{ "time": 0.8, "x": 0, "y": 0, "curve": "stepped" },
					{ "time": 1.6, "x": 0, "y": 0 }
				],
				"scale": [
					{ "time": 0, "x": 1, "y": 1, "curve": "stepped" },
					{ "time": 0.8, "x": 1, "y": 1, "curve": "stepped" },
					{ "time": 1.6, "x": 1, "y": 1 }
				]
			},
			"head": {
				"rotate": [
					{ "time": 0, "angle": 14.12 },
					{ "time": 0.4, "angle": 5.29 },
					{ "time": 0.8, "angle": 14.12 },
					{ "time": 1.2, "angle": 5.29 },
					{ "time": 1.6, "angle": 14.12 }
				],
				"translate": [
					{ "time": 0, "x": 0, "y": 0, "curve": "stepped" },
					{ "time": 0.8, "x": 0, "y": 0, "curve": "stepped" },
					{ "time": 1.6, "x": 0, "y": 0 }
				],
				"scale": [
					{ "time": 0, "x": 1, "y": 1, "curve": "stepped" },
					{ "time": 0.8, "x": 1, "y": 1, "curve": "stepped" },
					{ "time": 1.6, "x": 1, "y": 1 }
				]
			},
			"left_shoulder": {
				"rotate": [
					{ "time": 0, "angle": 27.09 },
					{ "time": 0.4, "angle": 331.97 },
					{ "time": 0.8, "angle": 27.09 },
					{ "time": 1.2, "angle": 331.97 },
					{ "time": 1.6, "angle": 27.09 }
				],
				"translate": [
					{ "time": 0, "x": 0, "y": 0, "curve": "stepped" },
					{ "time": 0.8, "x": 0, "y": 0, "curve": "stepped" },
					{ "time": 1.6, "x": 0, "y": 0 }
				],
				"scale": [
					{ "time": 0, "x": 1, "y": 1, "curve": "stepped" },
					{ "time": 0.8, "x": 1, "y": 1, "curve": "stepped" },
					{ "time": 1.6, "x": 1, "y": 1 }
				]
			},
			"right_shoulder": {
				"rotate": [
					{ "time": 0, "angle": 65.35 },
					{ "time": 0.4, "angle": -313.54 },
					{ "time": 0.8, "angle": 65.35 },
					{ "time": 1.2, "angle": -313.54 },
					{ "time": 1.6, "angle": 65.35 }
				],
				"translate": [
					{ "time": 0, "x": 0, "y": 0, "curve": "stepped" },
					{ "time": 0.8, "x": 0, "y": 0, "curve": "stepped" },
					{ "time": 1.6, "x": 0, "y": 0 }
				],
				"scale": [
					{ "time": 0, "x": 1, "y": 1, "curve": "stepped" },
					{ "time": 0.8, "x": 1, "y": 1, "curve": "stepped" },
					{ "time": 1.6, "x": 1, "y": 1 }
				]
			},
			"foot_left": {
				"rotate": [
					{ "time": 0, "angle": 0 },
					{ "time": 0.1, "angle": 8.62 },
					{ "time": 0.4333, "angle": -10.35 },
					{ "time": 0.8, "angle": 0 },
					{ "time": 0.9, "angle": 8.62 },
					{ "time": 1.2333, "angle": -10.35 },
					{ "time": 1.6, "angle": 0 }
				],
				"translate": [
					{ "time": 0, "x": 0, "y": 0, "curve": "stepped" },
					{ "time": 0.8, "x": 0, "y": 0, "curve": "stepped" },
					{ "time": 1.6, "x": 0, "y": 0 }
				],
				"scale": [
					{ "time": 0, "x": 1, "y": 1, "curve": "stepped" },
					{ "time": 0.8, "x": 1, "y": 1, "curve": "stepped" },
					{ "time": 1.6, "x": 1, "y": 1 }
				]
			},
			"foot_right": {
				"rotate": [
					{ "time": 0, "angle": -10.06 },
					{ "time": 0.5, "angle": 4.01 },
					{ "time": 0.7, "angle": 2.25 },
					{ "time": 0.8, "angle": -10.06 },
					{ "time": 1.3, "angle": 4.01 },
					{ "time": 1.5, "angle": 2.25 },
					{ "time": 1.6, "angle": -10.06 }
				],
				"translate": [
					{ "time": 0, "x": -0.3, "y": -0.73, "curve": "stepped" },
					{ "time": 0.8, "x": -0.3, "y": -0.73, "curve": "stepped" },
					{ "time": 1.6, "x": -0.3, "y": -0.73 }
				],
				"scale": [
					{ "time": 0, "x": 1, "y": 1, "curve": "stepped" },
					{ "time": 0.8, "x": 1, "y": 1, "curve": "stepped" },
					{ "time": 1.6, "x": 1, "y": 1 }
				]
			},
			"hair": {
				"rotate": [
					{ "time": 0, "angle": 3.57 },
					{ "time": 0.4, "angle": -7.51 },
					{ "time": 0.8, "angle": 3.57 },
					{ "time": 1.2, "angle": -7.51 },
					{ "time": 1.6, "angle": 3.57 }
				],
				"translate": [
					{ "time": 0, "x": 0, "y": 0, "curve": "stepped" },
					{ "time": 0.8, "x": 0, "y": 0, "curve": "stepped" },
					{ "time": 1.6, "x": 0, "y": 0 }
				],
				"scale": [
					{ "time": 0, "x": 1, "y": 1, "curve": "stepped" },
					{ "time": 0.8, "x": 1, "y": 1, "curve": "stepped" },
					{ "time": 1.6, "x": 1, "y": 1 }
				]
			},
			"left_arm": {
				"rotate": [
					{ "time": 0, "angle": -29.94 },
					{ "time": 0.4, "angle": -27.9 },
					{ "time": 0.8, "angle": -29.94 },
					{ "time": 1.2, "angle": -27.9 },
					{ "time": 1.6, "angle": -29.94 }
				],
				"translate": [
					{ "time": 0, "x": 0, "y": 0, "curve": "stepped" },
					{ "time": 0.8, "x": 0, "y": 0, "curve": "stepped" },
					{ "time": 1.6, "x": 0, "y": 0 }
				],
				"scale": [
					{ "time": 0, "x": 1, "y": 1, "curve": "stepped" },
					{ "time": 0.8, "x": 1, "y": 1, "curve": "stepped" },
					{ "time": 1.6, "x": 1, "y": 1 }
				]
			},
			"pony": {
				"rotate": [
					{ "time": 0, "angle": -3.46 },
					{ "time": 0.4, "angle": 4.57 },
					{ "time": 0.8, "angle": -3.46 },
					{ "time": 1.2, "angle": 4.57 },
					{ "time": 1.6, "angle": -3.46 }
				],
				"translate": [
					{ "time": 0, "x": 0, "y": 0, "curve": "stepped" },
					{ "time": 0.8, "x": 0, "y": 0, "curve": "stepped" },
					{ "time": 1.6, "x": 0, "y": 0 }
				],
				"scale": [
					{ "time": 0, "x": 1, "y": 1, "curve": "stepped" },
					{ "time": 0.8, "x": 1, "y": 1, "curve": "stepped" },
					{ "time": 1.6, "x": 1, "y": 1 }
				]
			},
			"right_arm": {
				"rotate": [
					{ "time": 0, "angle": 96.78 },
					{ "time": 0.4, "angle": 116.9 },
					{ "time": 0.8, "angle": 96.78 },
					{ "time": 1.2, "angle": 116.9 },
					{ "time": 1.6, "angle": 96.78 }
				],
				"translate": [
					{ "time": 0, "x": 0, "y": 0, "curve": "stepped" },
					{ "time": 0.8, "x": 0, "y": 0, "curve": "stepped" },
					{ "time": 1.6, "x": 0, "y": 0 }
				],
				"scale": [
					{ "time": 0, "x": 1, "y": 1, "curve": "stepped" },
					{ "time": 0.8, "x": 1, "y": 1, "curve": "stepped" },
					{ "time": 1.6, "x": 1, "y": 1 }
				]
			},
			"left_hand": {
				"rotate": [
					{ "time": 0, "angle": 0, "curve": "stepped" },
					{ "time": 0.8, "angle": 0, "curve": "stepped" },
					{ "time": 1.6, "angle": 0 }
				],
				"translate": [
					{ "time": 0, "x": 0, "y": 0, "curve": "stepped" },
					{ "time": 0.8, "x": 0, "y": 0, "curve": "stepped" },
					{ "time": 1.6, "x": 0, "y": 0 }
				],
				"scale": [
					{ "time": 0, "x": 1, "y": 1, "curve": "stepped" },
					{ "time": 0.8, "x": 1, "y": 1, "curve": "stepped" },
					{ "time": 1.6, "x": 1, "y": 1 }
				]
			},
			"right_hand": {
				"rotate": [
					{ "time": 0, "angle": 0, "curve": "stepped" },
					{ "time": 0.8, "angle": 0, "curve": "stepped" },
					{ "time": 1.6, "angle": 0 }
				],
				"translate": [
					{ "time": 0, "x": 0, "y": 0, "curve": "stepped" },
					{ "time": 0.8, "x": 0, "y": 0, "curve": "stepped" },
					{ "time": 1.6, "x": 0, "y": 0 }
				],
				"scale": [
					{ "time": 0, "x": 1, "y": 1, "curve": "stepped" },
					{ "time": 0.8, "x": 1, "y": 1, "curve": "stepped" },
					{ "time": 1.6, "x": 1, "y": 1 }
				]
			},
			"hip": {
				"rotate": [
					{ "time": 0, "angle": 0, "curve": "stepped" },
					{ "time": 0.8, "angle": 0, "curve": "stepped" },
					{ "time": 1.6, "angle": 0 }
				],
				"translate": [
					{ "time": 0, "x": 0, "y": -3.34 },
					{ "time": 0.0666, "x": 0, "y": -3.25 },
					{ "time": 0.1, "x": 0, "y": 0.25 },
					{ "time": 0.1333, "x": 0, "y": 5.97 },
					{ "time": 0.2, "x": 0, "y": 10.75 },
					{ "time": 0.3, "x": 0, "y": 13.41 },
					{ "time": 0.4, "x": 0, "y": 10.75 },
					{ "time": 0.5, "x": 0, "y": 8.42 },
					{ "time": 0.6, "x": 0, "y": 21.68 },
					{ "time": 0.7, "x": 0, "y": 19.72 },
					{ "time": 0.8, "x": 0, "y": -3.34 },
					{ "time": 0.8666, "x": 0, "y": -3.25 },
					{ "time": 0.9, "x": 0, "y": 0.25 },
					{ "time": 0.9333, "x": 0, "y": 5.97 },
					{ "time": 1, "x": 0, "y": 10.75 },
					{ "time": 1.1, "x": 0, "y": 13.41 },
					{ "time": 1.2, "x": 0, "y": 10.75 },
					{ "time": 1.3, "x": 0, "y": 8.42 },
					{ "time": 1.4, "x": 0, "y": 21.68 },
					{ "time": 1.5, "x": 0, "y": 19.72 },
					{ "time": 1.6, "x": 0, "y": -3.34 }
				],
				"scale": [
					{ "time": 0, "x": 1, "y": 1, "curve": "stepped" },
					{ "time": 0.8, "x": 1, "y": 1, "curve": "stepped" },
					{ "time": 1.6, "x": 1, "y": 1 }
				]
			}
		},
		"slots": {
			"head": {
				"attachment": [
					{ "time": 0, "name": "boss_skin/head" },
					{ "time": 0.5, "name": "boss_skin/faces/run" },
					{ "time": 0.9, "name": "boss_skin/head" }
				]
			},
			"weapon": {
				"attachment": [
					{ "time": 0, "name": "boss_skin/weapon" },
					{ "time": 0.8, "name": "boss_skin/weapon" }
				]
			}
		}
	},
	"scream": {
		"bones": {
			"right_shoulder": {
				"rotate": [
					{ "time": 0, "angle": 106.72 },
					{ "time": 0.2, "angle": -253.27 },
					{ "time": 0.5333, "angle": -282.22 },
					{ "time": 0.7, "angle": -63.32 },
					{ "time": 0.8666, "angle": -73.06 },
					{ "time": 1.1333, "angle": -54.44 },
					{ "time": 1.4, "angle": -78.43 },
					{ "time": 1.7, "angle": -52.56 },
					{ "time": 2, "angle": -63.32 },
					{ "time": 2.2666, "angle": -288.78 },
					{ "time": 3.0666, "angle": 31.94 }
				],
				"translate": [
					{ "time": 0, "x": 0, "y": 0 },
					{ "time": 0.7, "x": 5.46, "y": -4.14 },
					{ "time": 3.0666, "x": 0, "y": 0 }
				],
				"scale": [
					{ "time": 0, "x": 1, "y": 1, "curve": "stepped" },
					{ "time": 3.0666, "x": 1, "y": 1 }
				]
			},
			"right_arm": {
				"rotate": [
					{ "time": 0, "angle": 22.43, "curve": "stepped" },
					{ "time": 0.2, "angle": 22.43 },
					{ "time": 0.5333, "angle": -74.24 },
					{ "time": 0.7, "angle": 0.57 },
					{ "time": 0.8666, "angle": -22.81 },
					{ "time": 1.1333, "angle": -30.48 },
					{ "time": 1.4, "angle": -19.16 },
					{ "time": 1.7, "angle": -37.61 },
					{ "time": 2, "angle": 0.57 },
					{ "time": 2.2666, "angle": -85.86 },
					{ "time": 3.0666, "angle": 0.64 }
				],
				"translate": [
					{ "time": 0, "x": 0, "y": 0, "curve": "stepped" },
					{ "time": 3.0666, "x": 0, "y": 0 }
				],
				"scale": [
					{ "time": 0, "x": 1, "y": 1, "curve": "stepped" },
					{ "time": 3.0666, "x": 1, "y": 1 }
				]
			},
			"leg_left": {
				"rotate": [
					{ "time": 0, "angle": -63.96 },
					{ "time": 0.2, "angle": -1.73 },
					{ "time": 0.5333, "angle": -71.73 },
					{ "time": 0.7, "angle": 11.76 },
					{ "time": 0.9333, "angle": 8.91 },
					{ "time": 1.4666, "angle": 2.2 },
					{ "time": 1.7, "angle": 14.71 },
					{ "time": 2, "angle": 11.76 },
					{ "time": 2.2666, "angle": -63.05 },
					{ "time": 2.4666, "angle": -22.5 },
					{ "time": 2.6666, "angle": -43.05 },
					{ "time": 2.8666, "angle": -9.3 },
					{ "time": 3.0666, "angle": 9.21 }
				],
				"translate": [
					{ "time": 0, "x": 0, "y": 0, "curve": "stepped" },
					{ "time": 3.0666, "x": 0, "y": 0 }
				],
				"scale": [
					{ "time": 0, "x": 1, "y": 1, "curve": "stepped" },
					{ "time": 3.0666, "x": 1, "y": 1 }
				]
			},
			"calf_right": {
				"rotate": [
					{ "time": 0, "angle": 89.47 },
					{ "time": 0.2, "angle": -1.63 },
					{ "time": 0.5333, "angle": 96.27 },
					{ "time": 0.7, "angle": -2.69 },
					{ "time": 1.0333, "angle": 31.82 },
					{ "time": 1.3333, "angle": 44.32 },
					{ "time": 1.6666, "angle": 35.5 },
					{ "time": 1.8, "angle": 31.82 },
					{ "time": 2, "angle": -2.69 },
					{ "time": 2.2666, "angle": 119.66 },
					{ "time": 2.6666, "angle": 82.28 },
					{ "time": 2.8666, "angle": 56.54 },
					{ "time": 3.0666, "angle": -2.89 }
				],
				"translate": [
					{ "time": 0, "x": 0, "y": 0, "curve": "stepped" },
					{ "time": 3.0666, "x": 0, "y": 0 }
				],
				"scale": [
					{ "time": 0, "x": 1, "y": 1, "curve": "stepped" },
					{ "time": 3.0666, "x": 1, "y": 1 }
				]
			},
			"calf_left": {
				"rotate": [
					{ "time": 0, "angle": 78.19 },
					{ "time": 0.2, "angle": -3.76 },
					{ "time": 0.5333, "angle": 109.32 },
					{ "time": 0.7, "angle": 48.69 },
					{ "time": 0.9333, "angle": 71.02 },
					{ "time": 1.4666, "angle": 51.24 },
					{ "time": 1.7, "angle": 51.86 },
					{ "time": 2, "angle": 48.69 },
					{ "time": 2.2666, "angle": 65.62 },
					{ "time": 2.4666, "angle": 19.31 },
					{ "time": 2.6666, "angle": 67.57 },
					{ "time": 2.8666, "angle": 26.6 },
					{ "time": 3.0666, "angle": -3.74 }
				],
				"translate": [
					{ "time": 0, "x": 0, "y": 0, "curve": "stepped" },
					{ "time": 3.0666, "x": 0, "y": 0 }
				],
				"scale": [
					{ "time": 0, "x": 1, "y": 1, "curve": "stepped" },
					{ "time": 3.0666, "x": 1, "y": 1 }
				]
			},
			"root": {
				"rotate": [
					{ "time": 0, "angle": 0, "curve": "stepped" },
					{ "time": 3.0666, "angle": 0 }
				],
				"translate": [
					{ "time": 0, "x": 0, "y": 0, "curve": "stepped" },
					{ "time": 3.0666, "x": 0, "y": 0 }
				],
				"scale": [
					{ "time": 0, "x": 1, "y": 1, "curve": "stepped" },
					{ "time": 3.0666, "x": 1, "y": 1 }
				]
			},
			"head": {
				"rotate": [
					{ "time": 0, "angle": 0 },
					{ "time": 0.5333, "angle": 27.74 },
					{ "time": 0.7, "angle": -13.96 },
					{ "time": 1.1, "angle": -1.73 },
					{ "time": 2, "angle": -13.96 },
					{ "time": 2.0666, "angle": -1.73 },
					{ "time": 2.2666, "angle": 24.87, "curve": "stepped" },
					{ "time": 3.0666, "angle": 24.87 }
				],
				"translate": [
					{ "time": 0, "x": 0, "y": 0, "curve": "stepped" },
					{ "time": 3.0666, "x": 0, "y": 0 }
				],
				"scale": [
					{ "time": 0, "x": 1, "y": 1, "curve": "stepped" },
					{ "time": 3.0666, "x": 1, "y": 1 }
				]
			},
			"body": {
				"rotate": [
					{ "time": 0, "angle": 10.13, "curve": "stepped" },
					{ "time": 3.0666, "angle": 10.13 }
				],
				"translate": [
					{ "time": 0, "x": 0, "y": 0, "curve": "stepped" },
					{ "time": 3.0666, "x": 0, "y": 0 }
				],
				"scale": [
					{ "time": 0, "x": 1, "y": 1, "curve": "stepped" },
					{ "time": 3.0666, "x": 1, "y": 1 }
				]
			},
			"leg_right": {
				"rotate": [
					{ "time": 0, "angle": -76.62 },
					{ "time": 0.2, "angle": 0.19 },
					{ "time": 0.5333, "angle": -67.73 },
					{ "time": 0.7, "angle": -42.54 },
					{ "time": 1.0333, "angle": -53.38 },
					{ "time": 1.3333, "angle": -52.45 },
					{ "time": 1.6666, "angle": -60.91 },
					{ "time": 1.8, "angle": -53.38 },
					{ "time": 2, "angle": -42.54 },
					{ "time": 2.2666, "angle": -56.17 },
					{ "time": 2.6666, "angle": -24.22 },
					{ "time": 2.8666, "angle": -15.36 },
					{ "time": 3.0666, "angle": 9.7 }
				],
				"translate": [
					{ "time": 0, "x": 0, "y": 0, "curve": "stepped" },
					{ "time": 3.0666, "x": 0, "y": 0 }
				],
				"scale": [
					{ "time": 0, "x": 1, "y": 1, "curve": "stepped" },
					{ "time": 3.0666, "x": 1, "y": 1 }
				]
			},
			"left_shoulder": {
				"rotate": [
					{ "time": 0, "angle": -32.98 },
					{ "time": 0.2, "angle": 6.13 },
					{ "time": 0.5333, "angle": 332.65 },
					{ "time": 0.7, "angle": 39.68 },
					{ "time": 0.8, "angle": 61.17 },
					{ "time": 1.2, "angle": 43.31 },
					{ "time": 1.5666, "angle": 52.4 },
					{ "time": 2, "angle": 39.68 },
					{ "time": 2.2666, "angle": 322.62 },
					{ "time": 2.6666, "angle": 15.7 },
					{ "time": 3.0666, "angle": 6.87 }
				],
				"translate": [
					{ "time": 0, "x": 0, "y": 0, "curve": "stepped" },
					{ "time": 3.0666, "x": 0, "y": 0 }
				],
				"scale": [
					{ "time": 0, "x": 1, "y": 1, "curve": "stepped" },
					{ "time": 3.0666, "x": 1, "y": 1 }
				]
			},
			"hip": {
				"rotate": [
					{ "time": 0, "angle": 17.44 },
					{ "time": 0.2, "angle": 19.28 },
					{ "time": 0.5333, "angle": 4.27 },
					{ "time": 0.7, "angle": 5.01, "curve": "stepped" },
					{ "time": 2, "angle": 5.01 },
					{ "time": 2.2666, "angle": -24.22 },
					{ "time": 2.4666, "angle": -22.41 },
					{ "time": 2.6666, "angle": -8, "curve": "stepped" },
					{ "time": 3.0666, "angle": -8 }
				],
				"translate": [
					{ "time": 0, "x": 0, "y": -30.01 },
					{ "time": 0.2, "x": 0, "y": -0.76 },
					{ "time": 2.6666, "x": 0, "y": -14.32 },
					{ "time": 2.8666, "x": 0, "y": 8.87 },
					{ "time": 3.0666, "x": 0, "y": 14.88 }
				],
				"scale": [
					{ "time": 0, "x": 1, "y": 1, "curve": "stepped" },
					{ "time": 3.0666, "x": 1, "y": 1 }
				]
			},
			"hair": {
				"rotate": [
					{ "time": 0, "angle": 0, "curve": "stepped" },
					{ "time": 0.2666, "angle": 0, "curve": "stepped" },
					{ "time": 0.7666, "angle": 0 },
					{ "time": 1.0333, "angle": 167.22 },
					{ "time": 1.3333, "angle": 172.26 },
					{ "time": 1.6333, "angle": 157.26 },
					{ "time": 1.8, "angle": 167.22 },
					{ "time": 2.1, "angle": 0 },
					{ "time": 2.2666, "angle": 135.9, "curve": "stepped" },
					{
						"time": 2.6666,
						"angle": 135.9,
						"curve": [ 0, 0.94, 0.75, 1 ]
					},
					{ "time": 2.9333, "angle": -8.14 },
					{ "time": 3.0666, "angle": 0 }
				],
				"translate": [
					{ "time": 0, "x": 0, "y": 0, "curve": "stepped" },
					{ "time": 0.2666, "x": 0, "y": 0, "curve": "stepped" },
					{ "time": 0.7666, "x": 0, "y": 0 },
					{ "time": 0.8666, "x": -43.61, "y": 45.96 },
					{ "time": 0.9333, "x": -76.22, "y": 50.28 },
					{ "time": 1.0333, "x": -117.27, "y": 0.22, "curve": "stepped" },
					{ "time": 1.8, "x": -117.27, "y": 0.22 },
					{ "time": 1.9, "x": -78.12, "y": 35.44 },
					{ "time": 2, "x": -40.49, "y": 43.55 },
					{ "time": 2.1, "x": 0, "y": 0 },
					{ "time": 2.2666, "x": -93.48, "y": 27.32, "curve": "stepped" },
					{
						"time": 2.6666,
						"x": -93.48,
						"y": 27.32,
						"curve": [ 0, 0.46, 0.409, 0.78 ]
					},
					{
						"time": 2.8,
						"x": -7.81,
						"y": 6.7,
						"curve": [ 0.302, 0.92, 0.79, 1 ]
					},
					{ "time": 3.0666, "x": 0, "y": 0 }
				],
				"scale": [
					{ "time": 0, "x": 1, "y": 1, "curve": "stepped" },
					{ "time": 0.2666, "x": 1, "y": 1, "curve": "stepped" },
					{ "time": 0.7666, "x": 1, "y": 1, "curve": "stepped" },
					{ "time": 2.1, "x": 1, "y": 1, "curve": "stepped" },
					{ "time": 2.6666, "x": 1, "y": 1, "curve": "stepped" },
					{ "time": 3.0666, "x": 1, "y": 1 }
				]
			},
			"right_hand": {
				"rotate": [
					{ "time": 0, "angle": 0 },
					{ "time": 3.0666, "angle": 5.28 }
				],
				"translate": [
					{ "time": 0, "x": 0, "y": 0, "curve": "stepped" },
					{ "time": 3.0666, "x": 0, "y": 0 }
				],
				"scale": [
					{ "time": 0, "x": 1, "y": 1, "curve": "stepped" },
					{ "time": 3.0666, "x": 1, "y": 1 }
				]
			},
			"foot_right": {
				"rotate": [
					{ "time": 0, "angle": -24.48 },
					{ "time": 0.2, "angle": -4.94 },
					{ "time": 2.8666, "angle": 4.7, "curve": "stepped" },
					{ "time": 3.0666, "angle": 4.7 }
				],
				"translate": [
					{ "time": 0, "x": -1.06, "y": -1.64 },
					{ "time": 0.2, "x": 0.18, "y": -0.4, "curve": "stepped" },
					{ "time": 3.0666, "x": 0.18, "y": -0.4 }
				],
				"scale": [
					{ "time": 0, "x": 1, "y": 1, "curve": "stepped" },
					{ "time": 3.0666, "x": 1, "y": 1 }
				]
			},
			"left_arm": {
				"rotate": [
					{ "time": 0, "angle": -121.6 },
					{ "time": 0.2, "angle": -21.72 },
					{ "time": 0.5333, "angle": -108.82 },
					{ "time": 0.7, "angle": 5.62 },
					{ "time": 0.8, "angle": -47.33 },
					{ "time": 1.2, "angle": -64.43 },
					{ "time": 1.5666, "angle": -5.98 },
					{ "time": 2, "angle": 5.62 },
					{ "time": 2.2666, "angle": -66.56 },
					{ "time": 2.6666, "angle": -64.31 },
					{ "time": 3.0666, "angle": -40.48 }
				],
				"translate": [
					{ "time": 0, "x": 0, "y": 0, "curve": "stepped" },
					{ "time": 3.0666, "x": 0, "y": 0 }
				],
				"scale": [
					{ "time": 0, "x": 1, "y": 1, "curve": "stepped" },
					{ "time": 3.0666, "x": 1, "y": 1 }
				]
			},
			"foot_left": {
				"rotate": [
					{ "time": 0, "angle": -29.83 },
					{ "time": 0.2, "angle": 5.74 },
					{ "time": 2.6666, "angle": -17.98 },
					{ "time": 2.8666, "angle": -9.92 },
					{ "time": 3.0666, "angle": 1.18 }
				],
				"translate": [
					{ "time": 0, "x": -2.31, "y": -3.17 },
					{ "time": 0.2, "x": -1.33, "y": 0.16 },
					{ "time": 2.6666, "x": -1.64, "y": -0.63, "curve": "stepped" },
					{ "time": 3.0666, "x": -1.64, "y": -0.63 }
				],
				"scale": [
					{ "time": 0, "x": 1, "y": 1, "curve": "stepped" },
					{ "time": 3.0666, "x": 1, "y": 1 }
				]
			},
			"skirt": {
				"rotate": [
					{ "time": 0, "angle": -3.28, "curve": "stepped" },
					{ "time": 3.0666, "angle": -3.28 }
				],
				"translate": [
					{ "time": 0, "x": -14.33, "y": -18.21, "curve": "stepped" },
					{ "time": 3.0666, "x": -14.33, "y": -18.21 }
				],
				"scale": [
					{ "time": 0, "x": 1, "y": 1, "curve": "stepped" },
					{ "time": 3.0666, "x": 1, "y": 1 }
				]
			},
			"pony": {
				"rotate": [
					{ "time": 0, "angle": 0, "curve": "stepped" },
					{ "time": 1.1, "angle": 0 },
					{ "time": 1.2333, "angle": -5.32 },
					{ "time": 1.5, "angle": 1.64 },
					{ "time": 1.6333, "angle": 2.82 },
					{ "time": 1.7333, "angle": -5.65 },
					{ "time": 2.0666, "angle": 0 },
					{ "time": 2.1, "angle": 2.88 },
					{ "time": 3.0666, "angle": 0 }
				],
				"translate": [
					{ "time": 0, "x": 0, "y": 0, "curve": "stepped" },
					{ "time": 1.1, "x": 0, "y": 0, "curve": "stepped" },
					{ "time": 2.0666, "x": 0, "y": 0, "curve": "stepped" },
					{ "time": 3.0666, "x": 0, "y": 0 }
				],
				"scale": [
					{ "time": 0, "x": 1, "y": 1, "curve": "stepped" },
					{ "time": 1.1, "x": 1, "y": 1, "curve": "stepped" },
					{ "time": 2.0666, "x": 1, "y": 1, "curve": "stepped" },
					{ "time": 3.0666, "x": 1, "y": 1 }
				]
			},
			"left_hand": {
				"rotate": [
					{ "time": 0, "angle": 0, "curve": "stepped" },
					{ "time": 3.0666, "angle": 0 }
				],
				"translate": [
					{ "time": 0, "x": 0, "y": 0, "curve": "stepped" },
					{ "time": 3.0666, "x": 0, "y": 0 }
				],
				"scale": [
					{ "time": 0, "x": 1, "y": 1, "curve": "stepped" },
					{ "time": 3.0666, "x": 1, "y": 1 }
				]
			}
		},
		"slots": {
			"head": {
				"attachment": [
					{ "time": 0, "name": "boss_skin/head" },
					{ "time": 0.5333, "name": "boss_skin/faces/scream" },
					{ "time": 2.3, "name": "boss_skin/faces/jump" },
					{ "time": 2.8333, "name": "boss_skin/head" }
				]
			},
			"weapon": {
				"attachment": [
					{ "time": 0, "name": "boss_skin/weapon" }
				]
			}
		},
		"draworder": [
			{ "time": 0 },
			{ "time": 0.5333 },
			{
				"time": 3.0666,
				"offsets": [
					{ "slot": "head", "offset": 3 },
					{ "slot": "pony", "offset": 3 }
				]
			}
		]
	}
}
}