{
"bones": [
	{ "name": "root" },
	{ "name": "body", "parent": "root", "x": 1.94, "y": 121.12 },
	{ "name": "head", "parent": "body", "length": 128.9, "x": -0.99, "y": 100.49, "rotation": 94.95 },
	{ "name": "hip", "parent": "body", "length": 73.06, "x": 0.99, "y": -2.98, "rotation": -95.84 },
	{ "name": "left_shoulder", "parent": "body", "length": 76.98, "x": 70.64, "y": 88.55, "rotation": -75.74 },
	{ "name": "right_shoulder", "parent": "body", "length": 79.68, "x": -56.71, "y": 100.49, "rotation": -105.94 },
	{ "name": "helmet", "parent": "head", "length": 78.37, "x": 128.9, "y": 0.8, "rotation": -12.86 },
	{ "name": "left_arm", "parent": "left_shoulder", "length": 33.21, "x": 76.98, "y": -0.04, "rotation": -5.39 },
	{ "name": "left_leg", "parent": "hip", "length": 43.07, "x": 63.78, "y": 41.49, "rotation": 12.08 },
	{ "name": "right_arm", "parent": "right_shoulder", "length": 36.21, "x": 79.68, "y": -0.03 },
	{ "name": "right_leg", "parent": "hip", "length": 38.91, "x": 73.44, "y": -43.53, "rotation": 9.82 },
	{ "name": "left_hand", "parent": "left_arm", "length": 43.07, "x": 33.21, "y": -0.13, "rotation": -1.8 },
	{ "name": "right_hand", "parent": "right_arm", "length": 40.84, "x": 36.21, "y": -0.01, "rotation": 12.86 },
	{ "name": "schweif", "parent": "helmet", "length": 103.61, "x": 78.37, "y": -0.14, "rotation": -93.6 }
],
"slots": [
	{ "name": "right_shoulder", "bone": "right_shoulder", "attachment": "right_shoulder" },
	{ "name": "right_arm", "bone": "right_arm", "attachment": "right_arm" },
	{ "name": "right_hand", "bone": "right_hand", "attachment": "right_hand" },
	{ "name": "sword", "bone": "right_hand", "attachment": "sword" },
	{ "name": "schweif", "bone": "schweif", "attachment": "schweif" },
	{ "name": "foot_right", "bone": "right_leg", "attachment": "foot_right" },
	{ "name": "hip", "bone": "hip", "attachment": "hip" },
	{ "name": "foot_left", "bone": "left_leg", "attachment": "foot_left" },
	{ "name": "body", "bone": "body", "attachment": "body" },
	{ "name": "left_shoulder", "bone": "left_shoulder", "attachment": "left_shoulder" },
	{ "name": "left_arm", "bone": "left_arm", "attachment": "left_arm" },
	{ "name": "left_hand", "bone": "left_hand", "attachment": "left_hand" },
	{ "name": "shield", "bone": "left_hand", "attachment": "shield" },
	{ "name": "head", "bone": "head", "attachment": "head" },
	{ "name": "helmet", "bone": "helmet", "attachment": "helmet" },
	{ "name": "bb_ashbrett", "bone": "body", "attachment": "bb_ashbrett" }
],
"skins": {
	"default": {
		"bb_ashbrett": {
			"bb_ashbrett": {
				"type": "boundingbox",
				"vertices": [ -70.33075, -114.90883, 60.737194, -114.304825, 60.133205, 114.00705, -67.914734, 110.98706 ]
			}
		},
		"body": {
			"body": { "x": -1.39, "y": 38.39, "width": 160, "height": 162 }
		},
		"foot_left": {
			"foot_left": { "x": 24.16, "y": -3.24, "rotation": 83.76, "width": 69, "height": 53 }
		},
		"foot_right": {
			"foot_right": { "x": 19.32, "y": 0.19, "rotation": 86.01, "width": 64, "height": 62 }
		},
		"head": {
			"attack": { "x": 81.69, "y": -7.65, "scaleX": 0.951, "scaleY": 0.951, "rotation": -94.95, "width": 179, "height": 200 },
			"chase": { "x": 83.02, "y": -7.19, "rotation": -94.95, "width": 177, "height": 216 },
			"head": { "x": 90.23, "y": -9.9, "rotation": -94.95, "width": 174, "height": 197 },
			"success": { "x": 87.48, "y": -9.48, "scaleX": 0.982, "scaleY": 0.982, "rotation": -94.95, "width": 174, "height": 197 }
		},
		"helmet": {
			"helmet": { "x": 0.43, "y": -13.44, "rotation": -82.08, "width": 189, "height": 170 }
		},
		"hip": {
			"hip": { "x": 46.65, "y": 5.26, "rotation": 95.84, "width": 168, "height": 88 }
		},
		"left_arm": {
			"left_arm": { "x": 8.03, "y": 0.01, "rotation": 81.14, "width": 56, "height": 97 }
		},
		"left_hand": {
			"left_hand": { "x": 15.03, "y": -0.09, "rotation": 82.95, "width": 56, "height": 63 }
		},
		"left_shoulder": {
			"left_shoulder": { "x": 27.7, "y": -0.6, "rotation": 75.74, "width": 52, "height": 110 }
		},
		"right_arm": {
			"right_arm": { "x": 15.9, "y": -0.26, "rotation": 105.94, "width": 52, "height": 64 }
		},
		"right_hand": {
			"right_hand": { "x": 16.87, "y": 2.57, "rotation": 93.08, "width": 53, "height": 68 }
		},
		"right_shoulder": {
			"right_shoulder": { "x": 42.1, "y": -2.33, "rotation": 105.94, "width": 60, "height": 100 }
		},
		"schweif": {
			"schweif": { "x": 83.93, "y": -134.57, "rotation": 11.51, "width": 181, "height": 404 }
		},
		"shield": {
			"shield": { "x": 41.44, "y": -24.48, "scaleX": 1.324, "scaleY": 1.324, "rotation": 78.13, "width": 104, "height": 134 }
		},
		"sword": {
			"sword": { "x": 32.89, "y": -100.68, "rotation": 93.08, "width": 317, "height": 95 }
		}
	}
},
"animations": {
	"attack": {
		"bones": {
			"right_shoulder": {
				"rotate": [
					{ "time": 0, "angle": -4.18 },
					{ "time": 0.0666, "angle": 5.97 },
					{ "time": 0.1333, "angle": -4.18 },
					{ "time": 0.2333, "angle": 212.36 },
					{ "time": 0.3, "angle": -19.4 },
					{ "time": 0.6, "angle": -4.18, "curve": "stepped" },
					{ "time": 0.8333, "angle": -4.18 }
				],
				"translate": [
					{ "time": 0, "x": 0, "y": 0 },
					{ "time": 0.0666, "x": 0, "y": -7.83 },
					{ "time": 0.1333, "x": 0, "y": 0, "curve": "stepped" },
					{ "time": 0.6, "x": 0, "y": 0, "curve": "stepped" },
					{ "time": 0.8333, "x": 0, "y": 0 }
				],
				"scale": [
					{ "time": 0, "x": 1, "y": 1, "curve": "stepped" },
					{ "time": 0.1333, "x": 1, "y": 1, "curve": "stepped" },
					{ "time": 0.6, "x": 1, "y": 1, "curve": "stepped" },
					{ "time": 0.8333, "x": 1, "y": 1 }
				]
			},
			"root": {
				"rotate": [
					{ "time": 0, "angle": 0, "curve": "stepped" },
					{ "time": 0.6, "angle": 0, "curve": "stepped" },
					{ "time": 0.8333, "angle": 0 }
				],
				"translate": [
					{ "time": 0, "x": 0, "y": 0, "curve": "stepped" },
					{ "time": 0.6, "x": 0, "y": 0, "curve": "stepped" },
					{ "time": 0.8333, "x": 0, "y": 0 }
				],
				"scale": [
					{ "time": 0, "x": 1, "y": 1, "curve": "stepped" },
					{ "time": 0.6, "x": 1, "y": 1, "curve": "stepped" },
					{ "time": 0.8333, "x": 1, "y": 1 }
				]
			},
			"body": {
				"rotate": [
					{ "time": 0, "angle": 0, "curve": "stepped" },
					{ "time": 0.1333, "angle": 0 },
					{ "time": 0.3, "angle": 20.91 },
					{ "time": 0.3666, "angle": 20.63 },
					{ "time": 0.4333, "angle": 16.64 },
					{ "time": 0.6, "angle": 0, "curve": "stepped" },
					{ "time": 0.8333, "angle": 0 }
				],
				"translate": [
					{ "time": 0, "x": 0, "y": 0 },
					{ "time": 0.0666, "x": 0, "y": -28.73 },
					{ "time": 0.1333, "x": 0, "y": 0 },
					{ "time": 0.2333, "x": 0, "y": 129.29 },
					{ "time": 0.3, "x": -2.61, "y": 129.29 },
					{ "time": 0.4333, "x": -2.61, "y": 9.14 },
					{ "time": 0.4666, "x": -2.08, "y": 2.08 },
					{ "time": 0.5, "x": -1.56, "y": -4.96 },
					{ "time": 0.5666, "x": -0.52, "y": 0.95 },
					{ "time": 0.6, "x": 0, "y": 0, "curve": "stepped" },
					{ "time": 0.8333, "x": 0, "y": 0 }
				],
				"scale": [
					{ "time": 0, "x": 1, "y": 1, "curve": "stepped" },
					{ "time": 0.1333, "x": 1, "y": 1, "curve": "stepped" },
					{ "time": 0.6, "x": 1, "y": 1, "curve": "stepped" },
					{ "time": 0.8333, "x": 1, "y": 1 }
				]
			},
			"head": {
				"rotate": [
					{ "time": 0, "angle": 0, "curve": "stepped" },
					{ "time": 0.6, "angle": 0, "curve": "stepped" },
					{ "time": 0.8333, "angle": 0 }
				],
				"translate": [
					{ "time": 0, "x": 0, "y": 0 },
					{ "time": 0.0666, "x": 0, "y": -15.67 },
					{ "time": 0.2333, "x": 0, "y": -0.44 },
					{ "time": 0.4666, "x": 0, "y": -5.58 },
					{ "time": 0.6, "x": 0, "y": 0, "curve": "stepped" },
					{ "time": 0.8333, "x": 0, "y": 0 }
				],
				"scale": [
					{ "time": 0, "x": 1, "y": 1, "curve": "stepped" },
					{ "time": 0.6, "x": 1, "y": 1, "curve": "stepped" },
					{ "time": 0.8333, "x": 1, "y": 1 }
				]
			},
			"hip": {
				"rotate": [
					{ "time": 0, "angle": 0, "curve": "stepped" },
					{ "time": 0.6, "angle": 0, "curve": "stepped" },
					{ "time": 0.8333, "angle": 0 }
				],
				"translate": [
					{ "time": 0, "x": 0, "y": 0 },
					{ "time": 0.0666, "x": 3.91, "y": 15.67 },
					{ "time": 0.1333, "x": 3.91, "y": -2.61 },
					{ "time": 0.6, "x": 0, "y": 0, "curve": "stepped" },
					{ "time": 0.8333, "x": 0, "y": 0 }
				],
				"scale": [
					{ "time": 0, "x": 1, "y": 1, "curve": "stepped" },
					{ "time": 0.6, "x": 1, "y": 1, "curve": "stepped" },
					{ "time": 0.8333, "x": 1, "y": 1 }
				]
			},
			"left_shoulder": {
				"rotate": [
					{ "time": 0, "angle": 0 },
					{ "time": 0.2333, "angle": 115.89, "curve": "stepped" },
					{ "time": 0.3, "angle": 115.89 },
					{ "time": 0.6, "angle": 0, "curve": "stepped" },
					{ "time": 0.8333, "angle": 0 }
				],
				"translate": [
					{ "time": 0, "x": 0, "y": 0 },
					{ "time": 0.0666, "x": 0, "y": -10.44, "curve": "stepped" },
					{ "time": 0.3, "x": 0, "y": -10.44 },
					{ "time": 0.6, "x": 0, "y": 0, "curve": "stepped" },
					{ "time": 0.8333, "x": 0, "y": 0 }
				],
				"scale": [
					{ "time": 0, "x": 1, "y": 1, "curve": "stepped" },
					{ "time": 0.3, "x": 1, "y": 1, "curve": "stepped" },
					{ "time": 0.6, "x": 1, "y": 1, "curve": "stepped" },
					{ "time": 0.8333, "x": 1, "y": 1 }
				]
			},
			"helmet": {
				"rotate": [
					{ "time": 0, "angle": 0, "curve": "stepped" },
					{ "time": 0.6, "angle": 0, "curve": "stepped" },
					{ "time": 0.8333, "angle": 0 }
				],
				"translate": [
					{ "time": 0, "x": 0, "y": 0, "curve": "stepped" },
					{ "time": 0.6, "x": 0, "y": 0, "curve": "stepped" },
					{ "time": 0.8333, "x": 0, "y": 0 }
				],
				"scale": [
					{ "time": 0, "x": 1, "y": 1, "curve": "stepped" },
					{ "time": 0.6, "x": 1, "y": 1, "curve": "stepped" },
					{ "time": 0.8333, "x": 1, "y": 1 }
				]
			},
			"left_arm": {
				"rotate": [
					{ "time": 0, "angle": 0 },
					{ "time": 0.0666, "angle": -46.23 },
					{ "time": 0.2333, "angle": -3.1, "curve": "stepped" },
					{ "time": 0.3, "angle": -3.1 },
					{ "time": 0.6, "angle": 0, "curve": "stepped" },
					{ "time": 0.8333, "angle": 0 }
				],
				"translate": [
					{ "time": 0, "x": 0, "y": 0 },
					{ "time": 0.0666, "x": 0, "y": -23.1 },
					{ "time": 0.2333, "x": 11.52, "y": 0.69, "curve": "stepped" },
					{ "time": 0.3, "x": 11.52, "y": 0.69 },
					{ "time": 0.6, "x": 0, "y": 0, "curve": "stepped" },
					{ "time": 0.8333, "x": 0, "y": 0 }
				],
				"scale": [
					{ "time": 0, "x": 1, "y": 1, "curve": "stepped" },
					{ "time": 0.3, "x": 1, "y": 1, "curve": "stepped" },
					{ "time": 0.6, "x": 1, "y": 1, "curve": "stepped" },
					{ "time": 0.8333, "x": 1, "y": 1 }
				]
			},
			"left_leg": {
				"rotate": [
					{ "time": 0, "angle": 0, "curve": "stepped" },
					{ "time": 0.6, "angle": 0, "curve": "stepped" },
					{ "time": 0.8333, "angle": 0 }
				],
				"translate": [
					{ "time": 0, "x": 0, "y": 0 },
					{ "time": 0.0666, "x": -9.35, "y": 0 },
					{ "time": 0.1333, "x": 1.03, "y": 0 },
					{ "time": 0.6, "x": 0, "y": 0, "curve": "stepped" },
					{ "time": 0.8333, "x": 0, "y": 0 }
				],
				"scale": [
					{ "time": 0, "x": 1, "y": 1, "curve": "stepped" },
					{ "time": 0.6, "x": 1, "y": 1, "curve": "stepped" },
					{ "time": 0.8333, "x": 1, "y": 1 }
				]
			},
			"right_arm": {
				"rotate": [
					{ "time": 0, "angle": 0, "curve": "stepped" },
					{ "time": 0.6, "angle": 0, "curve": "stepped" },
					{ "time": 0.8333, "angle": 0 }
				],
				"translate": [
					{ "time": 0, "x": 0, "y": 0, "curve": "stepped" },
					{ "time": 0.6, "x": 0, "y": 0, "curve": "stepped" },
					{ "time": 0.8333, "x": 0, "y": 0 }
				],
				"scale": [
					{ "time": 0, "x": 1, "y": 1, "curve": "stepped" },
					{ "time": 0.6, "x": 1, "y": 1, "curve": "stepped" },
					{ "time": 0.8333, "x": 1, "y": 1 }
				]
			},
			"right_leg": {
				"rotate": [
					{ "time": 0, "angle": 0 },
					{ "time": 0.4333, "angle": -14.14 },
					{ "time": 0.5, "angle": -7.85 },
					{ "time": 0.5666, "angle": -2.58 },
					{ "time": 0.6, "angle": 0, "curve": "stepped" },
					{ "time": 0.8333, "angle": 0 }
				],
				"translate": [
					{ "time": 0, "x": 0, "y": 0 },
					{ "time": 0.0666, "x": -11.82, "y": 0 },
					{ "time": 0.1333, "x": 1.43, "y": 0 },
					{ "time": 0.4666, "x": -6.12, "y": 3.33 },
					{ "time": 0.5, "x": -12.59, "y": 3.33 },
					{ "time": 0.5333, "x": -6.06, "y": 3.33 },
					{ "time": 0.5666, "x": -2.22, "y": 3.33 },
					{ "time": 0.6, "x": 0, "y": 0, "curve": "stepped" },
					{ "time": 0.8333, "x": 0, "y": 0 }
				],
				"scale": [
					{ "time": 0, "x": 1, "y": 1, "curve": "stepped" },
					{ "time": 0.6, "x": 1, "y": 1, "curve": "stepped" },
					{ "time": 0.8333, "x": 1, "y": 1 }
				]
			},
			"left_hand": {
				"rotate": [
					{ "time": 0, "angle": 0 },
					{ "time": 0.0666, "angle": 61.24, "curve": "stepped" },
					{ "time": 0.3, "angle": 61.24 },
					{ "time": 0.6, "angle": 0, "curve": "stepped" },
					{ "time": 0.8333, "angle": 0 }
				],
				"translate": [
					{ "time": 0, "x": 0, "y": 0 },
					{ "time": 0.0666, "x": -22.47, "y": -28.66 },
					{ "time": 0.2333, "x": 14.14, "y": -2.46, "curve": "stepped" },
					{ "time": 0.3, "x": 14.14, "y": -2.46 },
					{ "time": 0.6, "x": 0, "y": 0, "curve": "stepped" },
					{ "time": 0.8333, "x": 0, "y": 0 }
				],
				"scale": [
					{ "time": 0, "x": 1, "y": 1, "curve": "stepped" },
					{ "time": 0.3, "x": 1, "y": 1, "curve": "stepped" },
					{ "time": 0.6, "x": 1, "y": 1, "curve": "stepped" },
					{ "time": 0.8333, "x": 1, "y": 1 }
				]
			},
			"right_hand": {
				"rotate": [
					{ "time": 0, "angle": 0, "curve": "stepped" },
					{ "time": 0.6, "angle": 0, "curve": "stepped" },
					{ "time": 0.8333, "angle": 0 }
				],
				"translate": [
					{ "time": 0, "x": 0, "y": 0, "curve": "stepped" },
					{ "time": 0.6, "x": 0, "y": 0, "curve": "stepped" },
					{ "time": 0.8333, "x": 0, "y": 0 }
				],
				"scale": [
					{ "time": 0, "x": 1, "y": 1, "curve": "stepped" },
					{ "time": 0.6, "x": 1, "y": 1, "curve": "stepped" },
					{ "time": 0.8333, "x": 1, "y": 1 }
				]
			},
			"schweif": {
				"rotate": [
					{ "time": 0, "angle": 0 },
					{ "time": 0.0666, "angle": 11.7 },
					{ "time": 0.2333, "angle": -9.64 },
					{ "time": 0.3333, "angle": 17.59 },
					{ "time": 0.4333, "angle": 12.85 },
					{ "time": 0.6, "angle": 0, "curve": "stepped" },
					{ "time": 0.8333, "angle": 0 }
				],
				"translate": [
					{ "time": 0, "x": 0, "y": 0, "curve": "stepped" },
					{ "time": 0.6, "x": 0, "y": 0, "curve": "stepped" },
					{ "time": 0.8333, "x": 0, "y": 0 }
				],
				"scale": [
					{ "time": 0, "x": 1, "y": 1, "curve": "stepped" },
					{ "time": 0.6, "x": 1, "y": 1, "curve": "stepped" },
					{ "time": 0.8333, "x": 1, "y": 1 }
				]
			}
		},
		"slots": {
			"head": {
				"attachment": [
					{ "time": 0, "name": "attack" },
					{ "time": 0.5333, "name": "success" }
				]
			}
		}
	},
	"close": {
		"bones": {
			"root": {
				"rotate": [
					{ "time": 0, "angle": 0, "curve": "stepped" },
					{ "time": 0.8, "angle": 0 }
				],
				"translate": [
					{ "time": 0, "x": 0, "y": 0, "curve": "stepped" },
					{ "time": 0.8, "x": 0, "y": 0 }
				],
				"scale": [
					{ "time": 0, "x": 1, "y": 1, "curve": "stepped" },
					{ "time": 0.8, "x": 1, "y": 1 }
				]
			},
			"body": {
				"rotate": [
					{ "time": 0, "angle": 42.49 },
					{ "time": 0.6, "angle": 23.63 },
					{ "time": 0.8, "angle": 42.49 }
				],
				"translate": [
					{ "time": 0, "x": 0, "y": 3.91 },
					{ "time": 0.6, "x": -0.73, "y": -4.9 },
					{ "time": 0.8, "x": 0, "y": 3.91 }
				],
				"scale": [
					{ "time": 0, "x": 1, "y": 1, "curve": "stepped" },
					{ "time": 0.8, "x": 1, "y": 1 }
				]
			},
			"head": {
				"rotate": [
					{ "time": 0, "angle": -11.88 },
					{ "time": 0.2333, "angle": -20.43 },
					{ "time": 0.4333, "angle": -11.88 }
				],
				"translate": [
					{ "time": 0, "x": -7.23, "y": -6.44 },
					{ "time": 0.2333, "x": -4.72, "y": -6.44 },
					{ "time": 0.4333, "x": -7.23, "y": -6.44 }
				],
				"scale": [
					{ "time": 0, "x": 1, "y": 1, "curve": "stepped" },
					{ "time": 0.4333, "x": 1, "y": 1 }
				]
			},
			"hip": {
				"rotate": [
					{ "time": 0, "angle": -9.2 },
					{ "time": 0.6, "angle": -3.02 },
					{ "time": 0.8, "angle": -9.2 }
				],
				"translate": [
					{ "time": 0, "x": 3.25, "y": -2.97, "curve": "stepped" },
					{ "time": 0.8, "x": 3.25, "y": -2.97 }
				],
				"scale": [
					{ "time": 0, "x": 1, "y": 1, "curve": "stepped" },
					{ "time": 0.8, "x": 1, "y": 1 }
				]
			},
			"left_shoulder": {
				"rotate": [
					{ "time": 0, "angle": -78.05 },
					{ "time": 0.6, "angle": 239.98 },
					{ "time": 0.8, "angle": -78.05 }
				],
				"translate": [
					{ "time": 0, "x": -12.54, "y": -25.13, "curve": "stepped" },
					{ "time": 0.8, "x": -12.54, "y": -25.13 }
				],
				"scale": [
					{ "time": 0, "x": 1, "y": 1, "curve": "stepped" },
					{ "time": 0.8, "x": 1, "y": 1 }
				]
			},
			"right_shoulder": {
				"rotate": [
					{ "time": 0, "angle": 255.02 },
					{ "time": 0.6, "angle": -26.62 },
					{ "time": 0.8, "angle": 255.02 }
				],
				"translate": [
					{ "time": 0, "x": 23.9, "y": -12.33, "curve": "stepped" },
					{ "time": 0.8, "x": 23.9, "y": -12.33 }
				],
				"scale": [
					{ "time": 0, "x": 1, "y": 1, "curve": "stepped" },
					{ "time": 0.8, "x": 1, "y": 1 }
				]
			},
			"left_arm": {
				"rotate": [
					{ "time": 0, "angle": -27.54 },
					{ "time": 0.6, "angle": -4.04 },
					{ "time": 0.8, "angle": -27.54 }
				],
				"translate": [
					{ "time": 0, "x": 3.22, "y": -10.62 },
					{ "time": 0.6, "x": 10.04, "y": 1.32 },
					{ "time": 0.8, "x": 3.22, "y": -10.62 }
				],
				"scale": [
					{ "time": 0, "x": 1, "y": 1, "curve": "stepped" },
					{ "time": 0.8, "x": 1, "y": 1 }
				]
			},
			"left_leg": {
				"rotate": [
					{ "time": 0, "angle": 27.99 },
					{ "time": 0.6, "angle": -40.51 },
					{ "time": 0.8, "angle": 27.99 }
				],
				"translate": [
					{ "time": 0, "x": -5.36, "y": -7.5 },
					{ "time": 0.6, "x": 17.32, "y": -7.05 },
					{ "time": 0.8, "x": -5.36, "y": -7.5 }
				],
				"scale": [
					{ "time": 0, "x": 1, "y": 1, "curve": "stepped" },
					{ "time": 0.8, "x": 1, "y": 1 }
				]
			},
			"right_arm": {
				"rotate": [
					{ "time": 0, "angle": -16.76 },
					{ "time": 0.6, "angle": -3.39 },
					{ "time": 0.8, "angle": -16.76 }
				],
				"translate": [
					{ "time": 0, "x": 0, "y": -3.5, "curve": "stepped" },
					{ "time": 0.8, "x": 0, "y": -3.5 }
				],
				"scale": [
					{ "time": 0, "x": 1, "y": 1, "curve": "stepped" },
					{ "time": 0.8, "x": 1, "y": 1 }
				]
			},
			"right_leg": {
				"rotate": [
					{ "time": 0, "angle": -26.52 },
					{ "time": 0.6, "angle": 54.39 },
					{ "time": 0.8, "angle": -26.52 }
				],
				"translate": [
					{ "time": 0, "x": -10.41, "y": 5.4 },
					{ "time": 0.6, "x": -16.87, "y": -3.79 },
					{ "time": 0.8, "x": -10.41, "y": 5.4 }
				],
				"scale": [
					{ "time": 0, "x": 1, "y": 1, "curve": "stepped" },
					{ "time": 0.8, "x": 1, "y": 1 }
				]
			},
			"left_hand": {
				"rotate": [
					{ "time": 0, "angle": 83.29 },
					{ "time": 0.6, "angle": 97.45 },
					{ "time": 0.8, "angle": 83.29 }
				],
				"translate": [
					{ "time": 0, "x": 9.51, "y": -22.67 },
					{ "time": 0.6, "x": 14.32, "y": -13.06 },
					{ "time": 0.8, "x": 9.51, "y": -22.67 }
				],
				"scale": [
					{ "time": 0, "x": 1, "y": 1, "curve": "stepped" },
					{ "time": 0.8, "x": 1, "y": 1 }
				]
			},
			"right_hand": {
				"rotate": [
					{ "time": 0, "angle": -14.76 },
					{ "time": 0.6, "angle": -10.26 },
					{ "time": 0.8, "angle": -14.76 }
				],
				"translate": [
					{ "time": 0, "x": 5.8, "y": -3.49 },
					{ "time": 0.6, "x": 5.8, "y": -1.4 },
					{ "time": 0.8, "x": 5.8, "y": -3.49 }
				],
				"scale": [
					{ "time": 0, "x": 1, "y": 1, "curve": "stepped" },
					{ "time": 0.8, "x": 1, "y": 1 }
				]
			},
			"schweif": {
				"rotate": [
					{ "time": 0, "angle": -8.44 },
					{ "time": 0.6, "angle": 18.51 },
					{ "time": 0.8, "angle": -8.44 }
				],
				"translate": [
					{ "time": 0, "x": 0, "y": 0 },
					{ "time": 0.6, "x": 11.24, "y": 6.2 },
					{ "time": 0.8, "x": 0, "y": 0 }
				],
				"scale": [
					{ "time": 0, "x": 1, "y": 1, "curve": "stepped" },
					{ "time": 0.8, "x": 1, "y": 1 }
				]
			},
			"helmet": {
				"rotate": [
					{ "time": 0, "angle": -16.24 },
					{ "time": 0.6, "angle": -0.54 },
					{ "time": 0.8, "angle": -16.24 }
				],
				"translate": [
					{ "time": 0, "x": 1.12, "y": -10 },
					{ "time": 0.6, "x": -2.68, "y": 0.36 },
					{ "time": 0.8, "x": 1.12, "y": -10 }
				],
				"scale": [
					{ "time": 0, "x": 1.081, "y": 1.081 },
					{ "time": 0.6, "x": 1.017, "y": 1.017 },
					{ "time": 0.8, "x": 1.081, "y": 1.081 }
				]
			}
		},
		"slots": {
			"head": {
				"attachment": [
					{ "time": 0, "name": "chase" }
				]
			}
		},
		"draworder": [
			{
				"time": 0,
				"offsets": [
					{ "slot": "shield", "offset": 1 }
				]
			},
			{
				"time": 0.1333,
				"offsets": [
					{ "slot": "head", "offset": -4 }
				]
			},
			{
				"time": 0.3333,
				"offsets": [
					{ "slot": "shield", "offset": 1 }
				]
			},
			{
				"time": 0.4333,
				"offsets": [
					{ "slot": "shield", "offset": 1 }
				]
			}
		]
	},
	"defend": {
		"bones": {
			"root": {
				"rotate": [
					{ "time": 0, "angle": 0, "curve": "stepped" },
					{ "time": 1, "angle": 0 }
				],
				"translate": [
					{ "time": 0, "x": 0, "y": 0, "curve": "stepped" },
					{ "time": 1, "x": 0, "y": 0 }
				],
				"scale": [
					{ "time": 0, "x": 1, "y": 1, "curve": "stepped" },
					{ "time": 1, "x": 1, "y": 1 }
				]
			},
			"body": {
				"rotate": [
					{ "time": 0, "angle": 0 },
					{ "time": 0.3666, "angle": 10.68, "curve": "stepped" },
					{
						"time": 0.7333,
						"angle": 10.68,
						"curve": [ 0.15, 0.6, 0.75, 1 ]
					},
					{ "time": 1, "angle": 0 }
				],
				"translate": [
					{ "time": 0, "x": 0, "y": 0 },
					{ "time": 0.3666, "x": -3.33, "y": -13.56, "curve": "stepped" },
					{
						"time": 0.7333,
						"x": -3.33,
						"y": -13.56,
						"curve": [ 0.15, 0.6, 0.75, 1 ]
					},
					{ "time": 1, "x": 0, "y": 0 }
				],
				"scale": [
					{ "time": 0, "x": 1, "y": 1, "curve": "stepped" },
					{ "time": 1, "x": 1, "y": 1 }
				]
			},
			"head": {
				"rotate": [
					{ "time": 0, "angle": 0 },
					{ "time": 0.3666, "angle": 4.08, "curve": "stepped" },
					{
						"time": 0.7333,
						"angle": 4.08,
						"curve": [ 0.15, 0.6, 0.75, 1 ]
					},
					{ "time": 1, "angle": 0 }
				],
				"translate": [
					{ "time": 0, "x": 0, "y": 0 },
					{ "time": 0.3666, "x": -1.29, "y": -15.86, "curve": "stepped" },
					{
						"time": 0.7333,
						"x": -1.29,
						"y": -15.86,
						"curve": [ 0.15, 0.6, 0.75, 1 ]
					},
					{ "time": 1, "x": 0, "y": 0 }
				],
				"scale": [
					{ "time": 0, "x": 1, "y": 1, "curve": "stepped" },
					{ "time": 1, "x": 1, "y": 1 }
				]
			},
			"hip": {
				"rotate": [
					{ "time": 0, "angle": 0 },
					{ "time": 0.3666, "angle": -10.74, "curve": "stepped" },
					{
						"time": 0.7333,
						"angle": -10.74,
						"curve": [ 0.15, 0.6, 0.75, 1 ]
					},
					{ "time": 1, "angle": 0 }
				],
				"translate": [
					{ "time": 0, "x": 0, "y": 0 },
					{ "time": 0.3666, "x": 5.22, "y": 0.7, "curve": "stepped" },
					{
						"time": 0.7333,
						"x": 5.22,
						"y": 0.7,
						"curve": [ 0.15, 0.6, 0.75, 1 ]
					},
					{ "time": 1, "x": 0, "y": 0 }
				],
				"scale": [
					{ "time": 0, "x": 1, "y": 1, "curve": "stepped" },
					{ "time": 1, "x": 1, "y": 1 }
				]
			},
			"left_shoulder": {
				"rotate": [
					{ "time": 0, "angle": 0 },
					{ "time": 0.3666, "angle": 251.15, "curve": "stepped" },
					{
						"time": 0.7333,
						"angle": 251.15,
						"curve": [ 0.15, 0.6, 0.75, 1 ]
					},
					{ "time": 1, "angle": 0 }
				],
				"translate": [
					{ "time": 0, "x": 0, "y": 0 },
					{ "time": 0.3666, "x": -15.82, "y": -6.66, "curve": "stepped" },
					{
						"time": 0.7333,
						"x": -15.82,
						"y": -6.66,
						"curve": [ 0.15, 0.6, 0.75, 1 ]
					},
					{ "time": 1, "x": 0, "y": 0 }
				],
				"scale": [
					{ "time": 0, "x": 1, "y": 1, "curve": "stepped" },
					{ "time": 1, "x": 1, "y": 1 }
				]
			},
			"right_shoulder": {
				"rotate": [
					{ "time": 0, "angle": 0 },
					{ "time": 0.3666, "angle": 44.67, "curve": "stepped" },
					{
						"time": 0.7333,
						"angle": 44.67,
						"curve": [ 0.15, 0.6, 0.75, 1 ]
					},
					{ "time": 1, "angle": 0 }
				],
				"translate": [
					{ "time": 0, "x": 0, "y": 0, "curve": "stepped" },
					{ "time": 1, "x": 0, "y": 0 }
				],
				"scale": [
					{ "time": 0, "x": 1, "y": 1, "curve": "stepped" },
					{ "time": 1, "x": 1, "y": 1 }
				]
			},
			"helmet": {
				"rotate": [
					{ "time": 0, "angle": 0, "curve": "stepped" },
					{ "time": 1, "angle": 0 }
				],
				"translate": [
					{ "time": 0, "x": 0, "y": 0, "curve": "stepped" },
					{ "time": 1, "x": 0, "y": 0 }
				],
				"scale": [
					{ "time": 0, "x": 1, "y": 1, "curve": "stepped" },
					{ "time": 1, "x": 1, "y": 1 }
				]
			},
			"left_arm": {
				"rotate": [
					{ "time": 0, "angle": 0 },
					{ "time": 0.3666, "angle": -21.97, "curve": "stepped" },
					{
						"time": 0.7333,
						"angle": -21.97,
						"curve": [ 0.15, 0.6, 0.75, 1 ]
					},
					{ "time": 1, "angle": 0 }
				],
				"translate": [
					{ "time": 0, "x": 0, "y": 0 },
					{ "time": 0.3666, "x": 8.44, "y": -3.92, "curve": "stepped" },
					{
						"time": 0.7333,
						"x": 8.44,
						"y": -3.92,
						"curve": [ 0.15, 0.6, 0.75, 1 ]
					},
					{ "time": 1, "x": 0, "y": 0 }
				],
				"scale": [
					{ "time": 0, "x": 1, "y": 1, "curve": "stepped" },
					{ "time": 1, "x": 1, "y": 1 }
				]
			},
			"left_leg": {
				"rotate": [
					{ "time": 0, "angle": 0 },
					{ "time": 0.3666, "angle": -4.9, "curve": "stepped" },
					{
						"time": 0.7333,
						"angle": -4.9,
						"curve": [ 0.15, 0.6, 0.75, 1 ]
					},
					{ "time": 1, "angle": 0 }
				],
				"translate": [
					{ "time": 0, "x": 0, "y": 0 },
					{ "time": 0.3666, "x": -10.68, "y": -1.93, "curve": "stepped" },
					{
						"time": 0.7333,
						"x": -10.68,
						"y": -1.93,
						"curve": [ 0.15, 0.6, 0.75, 1 ]
					},
					{ "time": 1, "x": 0, "y": 0 }
				],
				"scale": [
					{ "time": 0, "x": 1, "y": 1, "curve": "stepped" },
					{ "time": 1, "x": 1, "y": 1 }
				]
			},
			"right_arm": {
				"rotate": [
					{ "time": 0, "angle": 0 },
					{ "time": 0.3666, "angle": -121.87, "curve": "stepped" },
					{
						"time": 0.7333,
						"angle": -121.87,
						"curve": [ 0.15, 0.6, 0.75, 1 ]
					},
					{ "time": 1, "angle": 0 }
				],
				"translate": [
					{ "time": 0, "x": 0, "y": 0, "curve": "stepped" },
					{ "time": 1, "x": 0, "y": 0 }
				],
				"scale": [
					{ "time": 0, "x": 1, "y": 1, "curve": "stepped" },
					{ "time": 1, "x": 1, "y": 1 }
				]
			},
			"right_leg": {
				"rotate": [
					{ "time": 0, "angle": 0, "curve": "stepped" },
					{ "time": 1, "angle": 0 }
				],
				"translate": [
					{ "time": 0, "x": 0, "y": 0 },
					{ "time": 0.3666, "x": -16.57, "y": -1.7, "curve": "stepped" },
					{
						"time": 0.7333,
						"x": -16.57,
						"y": -1.7,
						"curve": [ 0.15, 0.6, 0.75, 1 ]
					},
					{ "time": 1, "x": 0, "y": 0 }
				],
				"scale": [
					{ "time": 0, "x": 1, "y": 1, "curve": "stepped" },
					{ "time": 1, "x": 1, "y": 1 }
				]
			},
			"left_hand": {
				"rotate": [
					{ "time": 0, "angle": 0 },
					{ "time": 0.3666, "angle": 90.63, "curve": "stepped" },
					{
						"time": 0.7333,
						"angle": 90.63,
						"curve": [ 0.15, 0.6, 0.75, 1 ]
					},
					{ "time": 1, "angle": 0 }
				],
				"translate": [
					{ "time": 0, "x": 0, "y": 0 },
					{ "time": 0.3666, "x": 36.05, "y": -24.04, "curve": "stepped" },
					{
						"time": 0.7333,
						"x": 36.05,
						"y": -24.04,
						"curve": [ 0.15, 0.6, 0.75, 1 ]
					},
					{ "time": 1, "x": 0, "y": 0 }
				],
				"scale": [
					{ "time": 0, "x": 1, "y": 1, "curve": "stepped" },
					{ "time": 1, "x": 1, "y": 1 }
				]
			},
			"right_hand": {
				"rotate": [
					{ "time": 0, "angle": 0, "curve": "stepped" },
					{ "time": 1, "angle": 0 }
				],
				"translate": [
					{ "time": 0, "x": 0, "y": 0, "curve": "stepped" },
					{ "time": 1, "x": 0, "y": 0 }
				],
				"scale": [
					{ "time": 0, "x": 1, "y": 1, "curve": "stepped" },
					{ "time": 1, "x": 1, "y": 1 }
				]
			},
			"schweif": {
				"rotate": [
					{ "time": 0, "angle": 0 },
					{
						"time": 0.3666,
						"angle": 7.82,
						"curve": [ 0.15, 0.6, 0.75, 1 ]
					},
					{ "time": 0.5333, "angle": -5.28 },
					{
						"time": 0.7333,
						"angle": -7.52,
						"curve": [ 0.15, 0.6, 0.75, 1 ]
					},
					{ "time": 0.9, "angle": -13.8 },
					{ "time": 1, "angle": 0 }
				],
				"translate": [
					{ "time": 0, "x": 0, "y": 0, "curve": "stepped" },
					{ "time": 1, "x": 0, "y": 0 }
				],
				"scale": [
					{ "time": 0, "x": 1, "y": 1, "curve": "stepped" },
					{ "time": 1, "x": 1, "y": 1 }
				]
			}
		},
		"draworder": [
			{
				"time": 0.2,
				"offsets": [
					{ "slot": "head", "offset": -4 }
				]
			},
			{
				"time": 0.3666,
				"offsets": [
					{ "slot": "shield", "offset": 2 },
					{ "slot": "head", "offset": -4 }
				]
			},
			{
				"time": 0.7333,
				"offsets": [
					{ "slot": "shield", "offset": 2 },
					{ "slot": "head", "offset": -4 }
				]
			}
		]
	},
	"idle": {
		"bones": {
			"root": {
				"rotate": [
					{ "time": 0, "angle": 0, "curve": "stepped" },
					{ "time": 1.5, "angle": 0 }
				],
				"translate": [
					{ "time": 0, "x": 0, "y": 0, "curve": "stepped" },
					{ "time": 1.5, "x": 0, "y": 0 }
				],
				"scale": [
					{ "time": 0, "x": 1, "y": 1, "curve": "stepped" },
					{ "time": 1.5, "x": 1, "y": 1 }
				]
			},
			"body": {
				"rotate": [
					{ "time": 0, "angle": 0, "curve": "stepped" },
					{ "time": 1.5, "angle": 0 }
				],
				"translate": [
					{ "time": 0, "x": 0, "y": 0, "curve": "stepped" },
					{ "time": 1.5, "x": 0, "y": 0 }
				],
				"scale": [
					{ "time": 0, "x": 1, "y": 1, "curve": "stepped" },
					{ "time": 1.5, "x": 1, "y": 1 }
				]
			},
			"head": {
				"rotate": [
					{ "time": 0, "angle": 0 },
					{ "time": 0.4, "angle": 32.4, "curve": "stepped" },
					{ "time": 1.2333, "angle": 32.4 },
					{ "time": 1.5, "angle": 0 }
				],
				"translate": [
					{ "time": 0, "x": 0, "y": 0 },
					{ "time": 0.4, "x": 6.79, "y": -0.84, "curve": "stepped" },
					{ "time": 1.2333, "x": 6.79, "y": -0.84 },
					{ "time": 1.5, "x": 0, "y": 0 }
				],
				"scale": [
					{ "time": 0, "x": 1, "y": 1, "curve": "stepped" },
					{ "time": 1.5, "x": 1, "y": 1 }
				]
			},
			"hip": {
				"rotate": [
					{ "time": 0, "angle": 0, "curve": "stepped" },
					{ "time": 1.5, "angle": 0 }
				],
				"translate": [
					{ "time": 0, "x": 0, "y": 0, "curve": "stepped" },
					{ "time": 1.5, "x": 0, "y": 0 }
				],
				"scale": [
					{ "time": 0, "x": 1, "y": 1, "curve": "stepped" },
					{ "time": 1.5, "x": 1, "y": 1 }
				]
			},
			"left_shoulder": {
				"rotate": [
					{ "time": 0, "angle": 0, "curve": "stepped" },
					{ "time": 1.5, "angle": 0 }
				],
				"translate": [
					{ "time": 0, "x": 0, "y": 0, "curve": "stepped" },
					{ "time": 1.5, "x": 0, "y": 0 }
				],
				"scale": [
					{ "time": 0, "x": 1, "y": 1, "curve": "stepped" },
					{ "time": 1.5, "x": 1, "y": 1 }
				]
			},
			"right_shoulder": {
				"rotate": [
					{ "time": 0, "angle": 0 },
					{ "time": 0.4, "angle": 15.65, "curve": "stepped" },
					{ "time": 1.2333, "angle": 15.65 },
					{ "time": 1.5, "angle": 0 }
				],
				"translate": [
					{ "time": 0, "x": 0, "y": -8.48, "curve": "stepped" },
					{ "time": 1.5, "x": 0, "y": -8.48 }
				],
				"scale": [
					{ "time": 0, "x": 1, "y": 1, "curve": "stepped" },
					{ "time": 1.5, "x": 1, "y": 1 }
				]
			},
			"helmet": {
				"rotate": [
					{ "time": 0, "angle": 0 },
					{ "time": 0.4, "angle": 4.02, "curve": "stepped" },
					{ "time": 1.2333, "angle": 4.02 },
					{ "time": 1.5, "angle": 0 }
				],
				"translate": [
					{ "time": 0, "x": 0, "y": 0 },
					{ "time": 0.4, "x": 1.54, "y": 2.02, "curve": "stepped" },
					{ "time": 1.2333, "x": 1.54, "y": 2.02 },
					{ "time": 1.5, "x": 0, "y": 0 }
				],
				"scale": [
					{ "time": 0, "x": 1, "y": 1, "curve": "stepped" },
					{ "time": 1.5, "x": 1, "y": 1 }
				]
			},
			"left_arm": {
				"rotate": [
					{ "time": 0, "angle": 0, "curve": "stepped" },
					{ "time": 1.5, "angle": 0 }
				],
				"translate": [
					{ "time": 0, "x": 0, "y": 0, "curve": "stepped" },
					{ "time": 1.5, "x": 0, "y": 0 }
				],
				"scale": [
					{ "time": 0, "x": 1, "y": 1, "curve": "stepped" },
					{ "time": 1.5, "x": 1, "y": 1 }
				]
			},
			"left_leg": {
				"rotate": [
					{ "time": 0, "angle": 0, "curve": "stepped" },
					{ "time": 1.5, "angle": 0 }
				],
				"translate": [
					{ "time": 0, "x": 0, "y": 0, "curve": "stepped" },
					{ "time": 1.5, "x": 0, "y": 0 }
				],
				"scale": [
					{ "time": 0, "x": 1, "y": 1, "curve": "stepped" },
					{ "time": 1.5, "x": 1, "y": 1 }
				]
			},
			"right_arm": {
				"rotate": [
					{ "time": 0, "angle": 0, "curve": "stepped" },
					{ "time": 1.5, "angle": 0 }
				],
				"translate": [
					{ "time": 0, "x": 0, "y": 0, "curve": "stepped" },
					{ "time": 1.5, "x": 0, "y": 0 }
				],
				"scale": [
					{ "time": 0, "x": 1, "y": 1, "curve": "stepped" },
					{ "time": 1.5, "x": 1, "y": 1 }
				]
			},
			"right_leg": {
				"rotate": [
					{ "time": 0, "angle": 0, "curve": "stepped" },
					{ "time": 0.6, "angle": 0, "curve": "stepped" },
					{ "time": 1.5, "angle": 0 }
				],
				"translate": [
					{ "time": 0, "x": 0, "y": 0, "curve": "stepped" },
					{ "time": 0.6, "x": 0, "y": 0 },
					{ "time": 0.7, "x": -16.63, "y": 0 },
					{ "time": 0.9666, "x": -1.1, "y": 0 },
					{ "time": 1.1, "x": -16.39, "y": 0 },
					{ "time": 1.3, "x": 0.32, "y": 0 },
					{ "time": 1.5, "x": 0, "y": 0 }
				],
				"scale": [
					{ "time": 0, "x": 1, "y": 1, "curve": "stepped" },
					{ "time": 0.6, "x": 1, "y": 1, "curve": "stepped" },
					{ "time": 1.5, "x": 1, "y": 1 }
				]
			},
			"left_hand": {
				"rotate": [
					{ "time": 0, "angle": 0, "curve": "stepped" },
					{ "time": 1.5, "angle": 0 }
				],
				"translate": [
					{ "time": 0, "x": 0, "y": 0, "curve": "stepped" },
					{ "time": 1.5, "x": 0, "y": 0 }
				],
				"scale": [
					{ "time": 0, "x": 1, "y": 1, "curve": "stepped" },
					{ "time": 1.5, "x": 1, "y": 1 }
				]
			},
			"right_hand": {
				"rotate": [
					{ "time": 0, "angle": 0, "curve": "stepped" },
					{ "time": 1.5, "angle": 0 }
				],
				"translate": [
					{ "time": 0, "x": 0, "y": 0, "curve": "stepped" },
					{ "time": 1.5, "x": 0, "y": 0 }
				],
				"scale": [
					{ "time": 0, "x": 1, "y": 1, "curve": "stepped" },
					{ "time": 1.5, "x": 1, "y": 1 }
				]
			},
			"schweif": {
				"rotate": [
					{ "time": 0, "angle": 0 },
					{ "time": 0.4, "angle": -12.35, "curve": "stepped" },
					{ "time": 1.2333, "angle": -12.35 },
					{ "time": 1.5, "angle": 0 }
				],
				"translate": [
					{ "time": 0, "x": 0, "y": 0 },
					{ "time": 0.4, "x": 6.73, "y": -7.73, "curve": "stepped" },
					{ "time": 1.2333, "x": 6.73, "y": -7.73 },
					{ "time": 1.5, "x": 0, "y": 0 }
				],
				"scale": [
					{ "time": 0, "x": 1, "y": 1, "curve": "stepped" },
					{ "time": 1.5, "x": 1, "y": 1 }
				]
			}
		}
	},
	"jump": {
		"bones": {
			"root": {
				"rotate": [
					{ "time": 0, "angle": 0, "curve": "stepped" },
					{ "time": 1.4, "angle": 0 }
				],
				"translate": [
					{ "time": 0, "x": 0, "y": 0, "curve": "stepped" },
					{ "time": 1.4, "x": 0, "y": 0 }
				],
				"scale": [
					{ "time": 0, "x": 1, "y": 1, "curve": "stepped" },
					{ "time": 1.4, "x": 1, "y": 1 }
				]
			},
			"body": {
				"rotate": [
					{ "time": 0, "angle": 0, "curve": "stepped" },
					{ "time": 0.3, "angle": 0 },
					{ "time": 0.5666, "angle": 22.26, "curve": "stepped" },
					{ "time": 0.8333, "angle": 22.26 },
					{ "time": 1.1, "angle": 0, "curve": "stepped" },
					{ "time": 1.4, "angle": 0 }
				],
				"translate": [
					{ "time": 0, "x": 0, "y": 0 },
					{ "time": 0.3, "x": 0, "y": -25.83 },
					{ "time": 0.8333, "x": -16.03, "y": 17.81 },
					{ "time": 1.1, "x": 0, "y": -25.83 },
					{ "time": 1.4, "x": 0, "y": 0 }
				],
				"scale": [
					{ "time": 0, "x": 1, "y": 1, "curve": "stepped" },
					{ "time": 0.3, "x": 1, "y": 1, "curve": "stepped" },
					{ "time": 0.8333, "x": 1, "y": 1, "curve": "stepped" },
					{ "time": 1.1, "x": 1, "y": 1, "curve": "stepped" },
					{ "time": 1.4, "x": 1, "y": 1 }
				]
			},
			"head": {
				"rotate": [
					{ "time": 0, "angle": 0, "curve": "stepped" },
					{ "time": 0.3, "angle": 0, "curve": "stepped" },
					{ "time": 0.8333, "angle": 0, "curve": "stepped" },
					{ "time": 1.1, "angle": 0, "curve": "stepped" },
					{ "time": 1.4, "angle": 0 }
				],
				"translate": [
					{ "time": 0, "x": 0, "y": -14.25, "curve": "stepped" },
					{ "time": 0.3, "x": 0, "y": -14.25 },
					{ "time": 0.5666, "x": 1.53, "y": -8.14 },
					{ "time": 0.8333, "x": 0, "y": -14.25, "curve": "stepped" },
					{ "time": 1.1, "x": 0, "y": -14.25, "curve": "stepped" },
					{ "time": 1.4, "x": 0, "y": -14.25 }
				],
				"scale": [
					{ "time": 0, "x": 1, "y": 1, "curve": "stepped" },
					{ "time": 0.3, "x": 1, "y": 1, "curve": "stepped" },
					{ "time": 0.8333, "x": 1, "y": 1, "curve": "stepped" },
					{ "time": 1.1, "x": 1, "y": 1, "curve": "stepped" },
					{ "time": 1.4, "x": 1, "y": 1 }
				]
			},
			"hip": {
				"rotate": [
					{ "time": 0, "angle": 0, "curve": "stepped" },
					{ "time": 1.4, "angle": 0 }
				],
				"translate": [
					{ "time": 0, "x": 0, "y": 0 },
					{ "time": 0.3, "x": 0, "y": 7.12 },
					{ "time": 0.5666, "x": -0.45, "y": -8.09, "curve": "stepped" },
					{ "time": 0.8333, "x": -0.45, "y": -8.09 },
					{ "time": 1.1, "x": 0, "y": 7.12 },
					{ "time": 1.4, "x": 0, "y": 0 }
				],
				"scale": [
					{ "time": 0, "x": 1, "y": 1, "curve": "stepped" },
					{ "time": 1.4, "x": 1, "y": 1 }
				]
			},
			"left_shoulder": {
				"rotate": [
					{ "time": 0, "angle": 0 },
					{ "time": 0.3, "angle": 10.84 },
					{ "time": 0.5666, "angle": -14.72 },
					{ "time": 0.8333, "angle": 10.84, "curve": "stepped" },
					{ "time": 1.1, "angle": 10.84 },
					{ "time": 1.4, "angle": 0 }
				],
				"translate": [
					{ "time": 0, "x": 0, "y": 0.89 },
					{ "time": 0.5666, "x": -0.45, "y": -14.32 },
					{ "time": 1.4, "x": 0, "y": 0.89 }
				],
				"scale": [
					{ "time": 0, "x": 1, "y": 1, "curve": "stepped" },
					{ "time": 1.4, "x": 1, "y": 1 }
				]
			},
			"right_shoulder": {
				"rotate": [
					{ "time": 0, "angle": 0 },
					{ "time": 0.3, "angle": 35.25 },
					{ "time": 0.5666, "angle": -2.94 },
					{ "time": 0.8333, "angle": 35.25, "curve": "stepped" },
					{ "time": 1.1, "angle": 35.25 },
					{ "time": 1.4, "angle": 0 }
				],
				"translate": [
					{ "time": 0, "x": 6.23, "y": 5.34 },
					{ "time": 0.3, "x": 0.89, "y": -12.47, "curve": "stepped" },
					{ "time": 0.8333, "x": 0.89, "y": -12.47, "curve": "stepped" },
					{ "time": 1.1, "x": 0.89, "y": -12.47 },
					{ "time": 1.4, "x": 6.23, "y": 5.34 }
				],
				"scale": [
					{ "time": 0, "x": 1, "y": 1, "curve": "stepped" },
					{ "time": 1.4, "x": 1, "y": 1 }
				]
			},
			"helmet": {
				"rotate": [
					{ "time": 0, "angle": 0, "curve": "stepped" },
					{ "time": 1.4, "angle": 0 }
				],
				"translate": [
					{ "time": 0, "x": 0, "y": 0, "curve": "stepped" },
					{ "time": 1.4, "x": 0, "y": 0 }
				],
				"scale": [
					{ "time": 0, "x": 1, "y": 1, "curve": "stepped" },
					{ "time": 1.4, "x": 1, "y": 1 }
				]
			},
			"left_arm": {
				"rotate": [
					{ "time": 0, "angle": 0 },
					{ "time": 0.3, "angle": -69.28 },
					{ "time": 0.5666, "angle": -27.99 },
					{ "time": 0.8333, "angle": -69.28, "curve": "stepped" },
					{ "time": 1.1, "angle": -69.28 },
					{ "time": 1.4, "angle": 0 }
				],
				"translate": [
					{ "time": 0, "x": 0, "y": 0 },
					{ "time": 0.3, "x": -8.97, "y": -23.35 },
					{ "time": 0.5666, "x": -0.2, "y": -8.62 },
					{ "time": 0.8333, "x": -8.97, "y": -23.35, "curve": "stepped" },
					{ "time": 1.1, "x": -8.97, "y": -23.35 },
					{ "time": 1.4, "x": 0, "y": 0 }
				],
				"scale": [
					{ "time": 0, "x": 1, "y": 1, "curve": "stepped" },
					{ "time": 1.4, "x": 1, "y": 1 }
				]
			},
			"left_leg": {
				"rotate": [
					{ "time": 0, "angle": 0, "curve": "stepped" },
					{ "time": 1.4, "angle": 0 }
				],
				"translate": [
					{ "time": 0, "x": 0, "y": 0 },
					{ "time": 0.3, "x": -11.52, "y": -1.17 },
					{ "time": 0.5666, "x": -3.07, "y": -0.87, "curve": "stepped" },
					{ "time": 0.8333, "x": -3.07, "y": -0.87 },
					{ "time": 1.1, "x": -11.52, "y": -1.17 },
					{ "time": 1.4, "x": 0, "y": 0 }
				],
				"scale": [
					{ "time": 0, "x": 1, "y": 1, "curve": "stepped" },
					{ "time": 1.4, "x": 1, "y": 1 }
				]
			},
			"right_arm": {
				"rotate": [
					{ "time": 0, "angle": 0 },
					{ "time": 0.3, "angle": -85.87 },
					{ "time": 0.5666, "angle": 1.91 },
					{ "time": 0.8333, "angle": -85.87, "curve": "stepped" },
					{ "time": 1.1, "angle": -85.87 },
					{ "time": 1.4, "angle": 0 }
				],
				"translate": [
					{ "time": 0, "x": 0, "y": 0, "curve": "stepped" },
					{ "time": 1.4, "x": 0, "y": 0 }
				],
				"scale": [
					{ "time": 0, "x": 1, "y": 1, "curve": "stepped" },
					{ "time": 1.4, "x": 1, "y": 1 }
				]
			},
			"right_leg": {
				"rotate": [
					{ "time": 0, "angle": 0, "curve": "stepped" },
					{ "time": 1.4, "angle": 0 }
				],
				"translate": [
					{ "time": 0, "x": 0, "y": 0 },
					{ "time": 0.3, "x": -17.72, "y": -1.8 },
					{ "time": 0.5666, "x": -5.1, "y": 0.04, "curve": "stepped" },
					{ "time": 0.8333, "x": -5.1, "y": 0.04 },
					{ "time": 1.1, "x": -17.72, "y": -1.8 },
					{ "time": 1.4, "x": 0, "y": 0 }
				],
				"scale": [
					{ "time": 0, "x": 1, "y": 1, "curve": "stepped" },
					{ "time": 1.4, "x": 1, "y": 1 }
				]
			},
			"left_hand": {
				"rotate": [
					{ "time": 0, "angle": 0 },
					{ "time": 0.3, "angle": 66.53, "curve": "stepped" },
					{ "time": 0.8333, "angle": 66.53, "curve": "stepped" },
					{ "time": 1.1, "angle": 66.53 },
					{ "time": 1.4, "angle": 0 }
				],
				"translate": [
					{ "time": 0, "x": 0, "y": 0 },
					{ "time": 0.3, "x": -13.06, "y": -26.32 },
					{ "time": 0.5666, "x": 5.41, "y": -18.89 },
					{ "time": 0.8333, "x": -13.06, "y": -26.32, "curve": "stepped" },
					{ "time": 1.1, "x": -13.06, "y": -26.32 },
					{ "time": 1.4, "x": 0, "y": 0 }
				],
				"scale": [
					{ "time": 0, "x": 1, "y": 1, "curve": "stepped" },
					{ "time": 1.4, "x": 1, "y": 1 }
				]
			},
			"right_hand": {
				"rotate": [
					{ "time": 0, "angle": 0 },
					{ "time": 0.3, "angle": -43.33 },
					{ "time": 0.5666, "angle": -3.72 },
					{ "time": 0.8333, "angle": -43.33, "curve": "stepped" },
					{ "time": 1.1, "angle": -43.33 },
					{ "time": 1.4, "angle": 0 }
				],
				"translate": [
					{ "time": 0, "x": 0, "y": 0 },
					{ "time": 0.5666, "x": 11.13, "y": 4.33 },
					{ "time": 1.4, "x": 0, "y": 0 }
				],
				"scale": [
					{ "time": 0, "x": 1, "y": 1, "curve": "stepped" },
					{ "time": 1.4, "x": 1, "y": 1 }
				]
			},
			"schweif": {
				"rotate": [
					{ "time": 0, "angle": 0 },
					{ "time": 0.3, "angle": 9.89 },
					{ "time": 0.5666, "angle": -14.57 },
					{ "time": 0.8333, "angle": -8.17 },
					{ "time": 1.1, "angle": 4.76 },
					{ "time": 1.4, "angle": 0 }
				],
				"translate": [
					{ "time": 0, "x": 0, "y": 0, "curve": "stepped" },
					{ "time": 1.4, "x": 0, "y": 0 }
				],
				"scale": [
					{ "time": 0, "x": 1, "y": 1, "curve": "stepped" },
					{ "time": 1.4, "x": 1, "y": 1 }
				]
			}
		}
	},
	"walk": {
		"bones": {
			"root": {
				"rotate": [
					{ "time": 0, "angle": 0, "curve": "stepped" },
					{ "time": 0.7333, "angle": 0 }
				],
				"translate": [
					{ "time": 0, "x": 0, "y": 0, "curve": "stepped" },
					{ "time": 0.7333, "x": 0, "y": 0 }
				],
				"scale": [
					{ "time": 0, "x": 1, "y": 1, "curve": "stepped" },
					{ "time": 0.7333, "x": 1, "y": 1 }
				]
			},
			"body": {
				"rotate": [
					{
						"time": 0,
						"angle": -8.09,
						"curve": [ 0.339, 0.64, 0.75, 1 ]
					},
					{ "time": 0.3333, "angle": -3.56 },
					{ "time": 0.7333, "angle": -8.09 }
				],
				"translate": [
					{
						"time": 0,
						"x": 0,
						"y": 0,
						"curve": [ 0.339, 0.64, 0.75, 1 ]
					},
					{ "time": 0.1333, "x": 0, "y": -15.6 },
					{ "time": 0.3333, "x": 0, "y": 13.09 },
					{ "time": 0.5333, "x": 0, "y": -0.43 },
					{ "time": 0.7333, "x": 0, "y": 0 }
				],
				"scale": [
					{ "time": 0, "x": 1, "y": 1, "curve": "stepped" },
					{ "time": 0.7333, "x": 1, "y": 1 }
				]
			},
			"head": {
				"rotate": [
					{
						"time": 0,
						"angle": 12.9,
						"curve": [ 0.339, 0.64, 0.75, 1 ]
					},
					{ "time": 0.3333, "angle": -1.84 },
					{ "time": 0.7333, "angle": 12.9 }
				],
				"translate": [
					{ "time": 0, "x": 0, "y": 0, "curve": "stepped" },
					{ "time": 0.7333, "x": 0, "y": 0 }
				],
				"scale": [
					{ "time": 0, "x": 1, "y": 1, "curve": "stepped" },
					{ "time": 0.7333, "x": 1, "y": 1 }
				]
			},
			"hip": {
				"rotate": [
					{ "time": 0, "angle": 0, "curve": "stepped" },
					{ "time": 0.7333, "angle": 0 }
				],
				"translate": [
					{ "time": 0, "x": 0, "y": 0, "curve": "stepped" },
					{ "time": 0.7333, "x": 0, "y": 0 }
				],
				"scale": [
					{ "time": 0, "x": 1, "y": 1, "curve": "stepped" },
					{ "time": 0.7333, "x": 1, "y": 1 }
				]
			},
			"left_shoulder": {
				"rotate": [
					{
						"time": 0,
						"angle": -2.16,
						"curve": [ 0.339, 0.64, 0.75, 1 ]
					},
					{ "time": 0.3333, "angle": 38.59 },
					{ "time": 0.7333, "angle": -2.16 }
				],
				"translate": [
					{ "time": 0, "x": -3.22, "y": -2.87, "curve": "stepped" },
					{ "time": 0.7333, "x": -3.22, "y": -2.87 }
				],
				"scale": [
					{ "time": 0, "x": 1, "y": 1, "curve": "stepped" },
					{ "time": 0.7333, "x": 1, "y": 1 }
				]
			},
			"right_shoulder": {
				"rotate": [
					{
						"time": 0,
						"angle": 83.7,
						"curve": [ 0.339, 0.64, 0.75, 1 ]
					},
					{ "time": 0.3333, "angle": 12.81 },
					{ "time": 0.7333, "angle": 83.7 }
				],
				"translate": [
					{ "time": 0, "x": -12.88, "y": -11.5, "curve": "stepped" },
					{ "time": 0.7333, "x": -12.88, "y": -11.5 }
				],
				"scale": [
					{ "time": 0, "x": 1, "y": 1, "curve": "stepped" },
					{ "time": 0.7333, "x": 1, "y": 1 }
				]
			},
			"helmet": {
				"rotate": [
					{
						"time": 0,
						"angle": 2.62,
						"curve": [ 0.339, 0.64, 0.75, 1 ]
					},
					{ "time": 0.3333, "angle": -0.81 },
					{ "time": 0.7333, "angle": 2.62 }
				],
				"translate": [
					{
						"time": 0,
						"x": 0.4,
						"y": 2.35,
						"curve": [ 0.339, 0.64, 0.75, 1 ]
					},
					{ "time": 0.3333, "x": 0.43, "y": -1.35 },
					{ "time": 0.7333, "x": 0.4, "y": 2.35 }
				],
				"scale": [
					{ "time": 0, "x": 1, "y": 1, "curve": "stepped" },
					{ "time": 0.7333, "x": 1, "y": 1 }
				]
			},
			"left_arm": {
				"rotate": [
					{
						"time": 0,
						"angle": -40.33,
						"curve": [ 0.318, 0.42, 0.666, 0.75 ]
					},
					{
						"time": 0.3333,
						"angle": -70.18,
						"curve": [ 0.377, 0.65, 0.734, 1 ]
					},
					{ "time": 0.7333, "angle": -40.33 }
				],
				"translate": [
					{
						"time": 0,
						"x": 1.65,
						"y": -21.47,
						"curve": [ 0.318, 0.42, 0.666, 0.75 ]
					},
					{
						"time": 0.3333,
						"x": -7.05,
						"y": -24.91,
						"curve": [ 0.377, 0.65, 0.734, 1 ]
					},
					{ "time": 0.7333, "x": 1.65, "y": -21.47 }
				],
				"scale": [
					{ "time": 0, "x": 1, "y": 1, "curve": "stepped" },
					{ "time": 0.7333, "x": 1, "y": 1 }
				]
			},
			"left_leg": {
				"rotate": [
					{
						"time": 0,
						"angle": 32.76,
						"curve": [ 0.339, 0.64, 0.75, 1 ]
					},
					{ "time": 0.3333, "angle": -25.39 },
					{ "time": 0.7333, "angle": 32.76 }
				],
				"translate": [
					{
						"time": 0,
						"x": -6.7,
						"y": -12.77,
						"curve": [ 0.339, 0.64, 0.75, 1 ]
					},
					{ "time": 0.3333, "x": 4.82, "y": 0.38 },
					{ "time": 0.7333, "x": -6.7, "y": -12.77 }
				],
				"scale": [
					{ "time": 0, "x": 1, "y": 1, "curve": "stepped" },
					{ "time": 0.7333, "x": 1, "y": 1 }
				]
			},
			"right_arm": {
				"rotate": [
					{
						"time": 0,
						"angle": -53.76,
						"curve": [ 0.339, 0.64, 0.75, 1 ]
					},
					{ "time": 0.3333, "angle": -49.07 },
					{ "time": 0.7333, "angle": -53.76 }
				],
				"translate": [
					{
						"time": 0,
						"x": 0,
						"y": 0,
						"curve": [ 0.339, 0.64, 0.75, 1 ]
					},
					{ "time": 0.3333, "x": 4.31, "y": -10.89 },
					{ "time": 0.7333, "x": 0, "y": 0 }
				],
				"scale": [
					{ "time": 0, "x": 1, "y": 1, "curve": "stepped" },
					{ "time": 0.7333, "x": 1, "y": 1 }
				]
			},
			"right_leg": {
				"rotate": [
					{
						"time": 0,
						"angle": -54.44,
						"curve": [ 0.339, 0.64, 0.75, 1 ]
					},
					{ "time": 0.3333, "angle": 56.81 },
					{ "time": 0.7333, "angle": -54.44 }
				],
				"translate": [
					{
						"time": 0,
						"x": -7.85,
						"y": -3.18,
						"curve": [ 0.339, 0.64, 0.75, 1 ]
					},
					{ "time": 0.3333, "x": -13.37, "y": -5.78 },
					{ "time": 0.7333, "x": -7.85, "y": -3.18 }
				],
				"scale": [
					{ "time": 0, "x": 1, "y": 1, "curve": "stepped" },
					{ "time": 0.7333, "x": 1, "y": 1 }
				]
			},
			"left_hand": {
				"rotate": [
					{ "time": 0, "angle": 61.13, "curve": "stepped" },
					{ "time": 0.7333, "angle": 61.13 }
				],
				"rotate": [
					{ "time": 0.7333, "angle": 61.13 }
				],
				"translate": [
					{ "time": 0, "x": -2.29, "y": -31, "curve": "stepped" },
					{ "time": 0.7333, "x": -2.29, "y": -31 }
				],
				"translate": [
					{ "time": 0.7333, "x": -2.29, "y": -31 }
				],
				"scale": [
					{ "time": 0, "x": 1, "y": 1, "curve": "stepped" },
					{ "time": 0.7333, "x": 1, "y": 1 }
				],
				"scale": [
					{ "time": 0.7333, "x": 1, "y": 1 }
				]
			},
			"right_hand": {
				"rotate": [
					{ "time": 0, "angle": 0, "curve": "stepped" },
					{ "time": 0.7333, "angle": 0 }
				],
				"translate": [
					{ "time": 0, "x": 0, "y": 0, "curve": "stepped" },
					{ "time": 0.7333, "x": 0, "y": 0 }
				],
				"scale": [
					{ "time": 0, "x": 1, "y": 1, "curve": "stepped" },
					{ "time": 0.7333, "x": 1, "y": 1 }
				]
			},
			"schweif": {
				"rotate": [
					{
						"time": 0,
						"angle": 11.67,
						"curve": [ 0.339, 0.64, 0.75, 1 ]
					},
					{ "time": 0.3333, "angle": -11.58 },
					{ "time": 0.7333, "angle": 11.67 }
				],
				"translate": [
					{ "time": 0, "x": 9.05, "y": 10.08, "curve": "stepped" },
					{ "time": 0.7333, "x": 9.05, "y": 10.08 }
				],
				"scale": [
					{ "time": 0, "x": 1, "y": 1, "curve": "stepped" },
					{ "time": 0.7333, "x": 1, "y": 1 }
				]
			}
		}
	}
}
}